old_src/full_adder.v
`timescale 1ns / 1ps

module full_adder(
    input a, 
    input b, 
    input cin, 
    output sum, 
    output cout
);

assign sum = a ^ b ^ cin;
assign cout = (a & b) | (b & cin) | (a & cin);

endmodule

old_src/rca_8bit.v
`timescale 1ns / 1ps

module rca_8bit(
    input [7:0] a,
    input [7:0] b,
    input cin,
    output [7:0] sum,
    output cout
);
    
    wire [6:0] c;

    full_adder fa0 (a[0], b[0], cin, sum[0], c[0]);
    full_adder fa1 (a[1], b[1], c[0], sum[1], c[1]);
    full_adder fa2 (a[2], b[2], c[1], sum[2], c[2]);
    full_adder fa3 (a[3], b[3], c[2], sum[3], c[3]);
    full_adder fa4 (a[4], b[4], c[3], sum[4], c[4]);
    full_adder fa5 (a[5], b[5], c[4], sum[5], c[5]);
    full_adder fa6 (a[6], b[6], c[5], sum[6], c[6]);
    full_adder fa7 (a[7], b[7], c[6], sum[7], cout);

endmodule

old_src/rca_16bit.v
`timescale 1ns / 1ps

module rca_16bit(
    input [15:0] a,
    input [15:0] b,
    input cin,
    output [15:0] sum,
    output cout
);
    
    wire c8;
    
    rca_8bit low (a[7:0], b[7:0], cin, sum[7:0], c8);
    rca_8bit high (a[15:8], b[15:8], c8, sum[15:8], cout);

endmodule

old_src/sim_rca_16bit_exponential.v
`timescale 1ns/1ps

module sim_rca_16bit_exponential;

    reg  [15:0] a, b;
    reg cin;
    wire [15:0] sum;
    wire cout;

    // Arquivos
    integer in_file;
    integer out_file;
    integer r;
    
    rca_16bit DUT (
        .a(a),
        .b(b),
        .cin(cin),
        .sum(sum),
        .cout(cout)
    );

        // Caminhos de arquivo de entrada e saída
    reg [1023:0] input_file  = "/home/tiago/energetic_efficiency/data/16_exponential.txt";
    reg [1023:0] output_file = "/home/tiago/energetic_efficiency/results/rca_16bit_exponential.txt";
    
    initial begin
        // Abre arquivos
        in_file  = $fopen(input_file, "r");
        out_file = $fopen(output_file, "w");

        if(in_file == 0) begin
            $display("Erro ao abrir arquivo de entrada: %s", input_file);
            $finish;
        end
        if(out_file == 0) begin
            $display("Erro ao abrir arquivo de saída: %s", output_file);
            $finish;
        end

        $display("Simulação iniciada: %s -> %s", input_file, output_file);

        // fixa o carry-in
        cin = 0;

        // Processamento Sequencial Sem Clock Rápido
        while (!$feof(in_file)) begin
            // 1. Lê os dados do arquivo
            r = $fscanf(in_file, "%h %h\n", a, b);
            
            // 2. Aguarda um tempo para a lógica combinacional estabilizar
            // 10ns é mais que suficiente para um RCA de 16 bits na Spartan-7
            #10; 
            
            // 3. Grava a entrada E a saída resultante na mesma linha
            $fwrite(out_file, "%h %h %b %h %b\n", a, b, cin, sum, cout);
        end

        $fclose(in_file);
        $fclose(out_file);

        $display("Simulação concluída.");
        $finish;
    end

endmodule

results/sim_rca_16bit_exponential.vcd
$date
   Wed Mar 18 13:38:54 2026
$end
$version
  2022.1
$end
$timescale
  1ps
$end
$scope module sim_rca_16bit_exponential $end
$var reg 16 ! a [15:0] $end
$var reg 16 " b [15:0] $end
$var reg 1 # cin $end
$var wire 16 $ sum [15:0] $end
$var wire 1 % cout $end
$var integer 32 & in_file [31:0] $end
$var integer 32 ' out_file [31:0] $end
$var integer 32 ( r [31:0] $end
$var reg 1024 ) input_file [1023:0] $end
$var reg 1024 * output_file [1023:0] $end
$upscope $end
$enddefinitions $end
#0
$dumpvars
b1111011010 !
b100011100110111 "
0#
b100101100010001 $
0%
b11111111111111111011000111100000 &
b11111111111111111011000111100001 '
b10 (
b10111101101000011011110110110101100101001011110111010001101001011000010110011101101111001011110110010101101110011001010111001001100111011001010111010001101001011000110101111101100101011001100110011001101001011000110110100101100101011011100110001101111001001011110110010001100001011101000110000100101111001100010011011001011111011001010111100001110000011011110110111001100101011011100111010001101001011000010110110000101110011101000111100001110100 )
b1011110110100001101111011011010110010100101111011101000110100101100001011001110110111100101111011001010110111001100101011100100110011101100101011101000110100101100011010111110110010101100110011001100110100101100011011010010110010101101110011000110111100100101111011100100110010101110011011101010110110001110100011100110010111101110010011000110110000101011111001100010011011001100010011010010111010001011111011001010111100001110000011011110110111001100101011011100111010001101001011000010110110000101110011101000111100001110100 *
$end
#10000
b101100011 !
b100011100110111 "
b100100010011010 $
#20000
b100011010000111 !
b100011100110111 "
b1000110110111110 $
#30000
b111111101001 !
b100011100110111 "
b101011100100000 $
#40000
b111111101001 !
b1101001100101 "
b10101001001110 $
#50000
b111111101001 !
b1101001100101 "
#60000
b111111101001 !
b1101001100101 "
#70000
b111111101001 !
b1101001100101 "
#80000
b111001101100 !
b1101001100101 "
b10100011010001 $
#90000
b111001101100 !
b1101001100101 "
#100000
b101010111000001 !
b1000001001001 "
b110011000001010 $
#110000
b101010111000001 !
b10110001111010 "
b1000001000111011 $
#120000
b1101111110010 !
b1001100010110 "
b10111100001000 $
#130000
b110010001101 !
b1001100010110 "
b1111110100011 $
#140000
b110010001101 !
b1001100010110 "
#150000
b110010001101 !
b100111110000101 "
b101110000010010 $
#160000
b110010001101 !
b100000001010 "
b1010010010111 $
#170000
b110010001101 !
b100000001010 "
#180000
b110010001101 !
b100000001010 "
#190000
b1011000110010 !
b100110111011100 "
b110010000001110 $
#200000
b10000001011 !
b100110111011100 "
b101000111100111 $
#210000
b10000001011 !
b10111010110000 "
b11001010111011 $
#220000
b10000001011 !
b101111011101 "
b111111101000 $
#230000
b10000001011 !
b11000100010 "
b101000101101 $
#240000
b10000001011 !
b1000010010 "
b11000011101 $
#250000
b10000001011 !
b1101011000011 "
b1111011001110 $
#260000
b101111100011101 !
b1101011010011 "
b111100111110000 $
#270000
b101111100011101 !
b1101011010011 "
#280000
b101111100011101 !
b100000101011 "
b110011101001000 $
#290000
b100011000010110 !
b1100100000 "
b100100100110110 $
#300000
b100011000010110 !
b101011001101 "
b101000011100011 $
#310000
b101001001001 !
b11100001111 "
b1000101011000 $
#320000
b101001001001 !
b11100001111 "
#330000
b101001001001 !
b11100001111 "
#340000
b101001001001 !
b11100001111 "
#350000
b101001001001 !
b11100001111 "
#360000
b1010011001010 !
b1101001111011 "
b10111101000101 $
#370000
b110111110100 !
b10100010000011 "
b11011001110111 $
#380000
b1000111101000 !
b10100010000011 "
b11101001101011 $
#390000
b101100001011 !
b10100010000011 "
b11001110001110 $
#400000
b111011111100 !
b100110001110 "
b1100010001010 $
#410000
b111011111100 !
b110000110111 "
b1101100110011 $
#420000
b111011111100 !
b110000110111 "
#430000
b111011111100 !
b110000110111 "
#440000
b11100101110 !
b1100001101100101 "
b1100101010010011 $
#450000
b11100101110 !
b11000101101111 "
b11100010011101 $
#460000
b11100101110 !
b11000101101111 "
#470000
b11100101110 !
b11110100010111 "
b100010001000101 $
#480000
b110001100011001 !
b100001110111011 "
b1010011011010100 $
#490000
b1000101110000 !
b100001110111011 "
b101010100101011 $
#500000
b1000101110000 !
b100001110111011 "
#510000
b1011100100 !
b100001110111011 "
b100011010011111 $
#520000
b1011100100 !
b100101000001 "
b110000100101 $
#530000
b1011100100 !
b11111000101001 "
b100000100001101 $
#540000
b1011100100 !
b11111000101001 "
#550000
b1011100100 !
b10001101000001 "
b10011000100101 $
#560000
b110010000011 !
b10100001011 "
b1000110001110 $
#570000
b110000110 !
b10100001011 "
b11010010001 $
#580000
b100111111110100 !
b10100001011 "
b101010011111111 $
#590000
b100000010111 !
b10100001011 "
b110100100010 $
#600000
b100000010111 !
b1110011010011 "
b10010011101010 $
#610000
b10010010101010 !
b10100100111010 "
b100110111100100 $
#620000
b100111001001110 !
b10100100111010 "
b111011110001000 $
#630000
b1000001000001 !
b10100100111010 "
b11100101111011 $
#640000
b1000001000001 !
b10100100111010 "
#650000
b1000001000001 !
b10101000011100 "
b11101001011101 $
#660000
b101110111000 !
b11010011011101 "
b100000010010101 $
#670000
b101110111000 !
b11010011011101 "
#680000
b101110111000 !
b101100101 "
b110100011101 $
#690000
b111000001111010 !
b101100101 "
b111000111011111 $
#700000
b111000001111010 !
b10000010100111 "
b1001000100100001 $
#710000
b111101111011 !
b10000010100111 "
b11000000100010 $
#720000
b1010100 !
b110101110110 "
b110111001010 $
#730000
b1010100 !
b10000000010001 "
b10000001100101 $
#740000
b1110010111101 !
b1000000101100010 "
b1001111000011111 $
#750000
b1110010111101 !
b1000000101100010 "
#760000
b1110010111101 !
b10101010011 "
b10001000010000 $
#770000
b111110101010 !
b10101101100100 "
b11101100001110 $
#780000
b111110101010 !
b10111110101111 "
b11111101011001 $
#790000
b111110101010 !
b110011100110 "
b1110010010000 $
#800000
b111110101010 !
b10110011010000 "
b11110001111010 $
#810000
b1101000101111 !
b10110101001 "
b1111111011000 $
#820000
b1101000101111 !
b10000001101101 "
b11101010011100 $
#830000
b101111110100 !
b10000001101101 "
b10110001100001 $
#840000
b101111110100 !
b101111100111 "
b1011111011011 $
#850000
b100100101001011 !
b11100010110011 "
b1000000111111110 $
#860000
b11001000001 !
b11100010110011 "
b11111011110100 $
#870000
b100111110010 !
b11100010110011 "
b100001010100101 $
#880000
b100111110010 !
b11100010110011 "
#890000
b100111110010 !
b11101001000011 "
b100010000110101 $
#900000
b111111010000010 !
b11101001000011 "
b1011100011000101 $
#910000
b1011011110011 !
b11101001000011 "
b101000100110110 $
#920000
b1011011110011 !
b11101001000011 "
#930000
b1011011110011 !
b11101001000011 "
#940000
b1011011110011 !
b1100010101101 "
b10111110100000 $
#950000
b1011011110011 !
b1100010101101 "
#960000
b10000111001000 !
b1000100010010 "
b11001011011010 $
#970000
b1001110101001 !
b1001111000111 "
b10011101110000 $
#980000
b1110010011000 !
b1001111000111 "
b11000001011111 $
#990000
b1110010011000 !
b1001111000111 "
#1000000
b1110010011000 !
b1001111000111 "
#1010000
b10110010110101 !
b11111111001101 "
b110110010000010 $
#1020000
b10110010110101 !
b11111111001101 "
#1030000
b111110011011110 !
b11111111001101 "
b1011110010101011 $
#1040000
b1011011101101100 !
b1110000000100 "
b1101001101110000 $
#1050000
b1111111111101 !
b1110000000100 "
b11110000000001 $
#1060000
b1111111111101 !
b1110000000100 "
#1070000
b1000100010 !
b1110000000100 "
b1111000100110 $
#1080000
b100100101011 !
b1110000000100 "
b10010100101111 $
#1090000
b100100101011 !
b1110000000100 "
#1100000
b100100101011 !
b1110000000100 "
#1110000
b100100101011 !
b1010111 "
b100110000010 $
#1120000
b100100101011 !
b1010111 "
#1130000
b100110010000100 !
b1010111 "
b100110011011011 $
#1140000
b10011101111 !
b101000010011001 "
b101010110001000 $
#1150000
b1001001001011 !
b10011110011 "
b1011100111110 $
#1160000
b1001001001011 !
b1100000111111 "
b10101010001010 $
#1170000
b10100100110100 !
b10111000100100 "
b101011101011000 $
#1180000
b1100110011011 !
b10010111011010 "
b11111101110101 $
#1190000
b1100110011011 !
b10010111011010 "
#1200000
b10110010001101 !
b10010111011010 "
b101001001100111 $
#1210000
b1010011111 !
b1001100010010 "
b1010110110001 $
#1220000
b1001111100 !
b1000000110 "
b10010000010 $
#1230000
b111011111101 !
b1000000110 "
b1000100000011 $
#1240000
b111011111101 !
b10001001001111 "
b11000101001100 $
#1250000
b111011111101 !
b1111010100001 "
b10110110011110 $
#1260000
b1000101011001 !
b1111010100001 "
b10111111111010 $
#1270000
b10011111011010 !
b101001000010001 "
b111100111101011 $
#1280000
b10011111011010 !
b11100111 "
b10100011000001 $
#1290000
b1011010011100 !
b11100111 "
b1011110000011 $
#1300000
b1011010011100 !
b100100010011 "
b1111110101111 $
#1310000
b1010101010000 !
b100111001001 "
b1111100011001 $
#1320000
b1010101010000 !
b100111001001 "
#1330000
b10010000010001 !
b11100100 "
b10010011110101 $
#1340000
b110111101001001 !
b11100100 "
b111000000101101 $
#1350000
b110111101001001 !
b11100100 "
#1360000
b110111101001001 !
b10010100100 "
b111001111101101 $
#1370000
b110111101001001 !
b10010100100 "
#1380000
b11000000001001 !
b10010100100 "
b11010010101101 $
#1390000
b11000000001001 !
b1110010111000 "
b100110011000001 $
#1400000
b111111101001 !
b1110010111000 "
b10110010100001 $
#1410000
b111110000011 !
b1110001011110 "
b10101111100001 $
#1420000
b11011110011100 !
b1110001011110 "
b101001111111010 $
#1430000
b101100001001 !
b1110001011110 "
b10011101100111 $
#1440000
b100010111110110 !
b11010110011000 "
b111101110001110 $
#1450000
b10110000011110 !
b11010110011000 "
b110000110110110 $
#1460000
b10110000011110 !
b11010110011000 "
#1470000
b10011010100011 !
b11010110011000 "
b101110000111011 $
#1480000
b1000011010111 !
b11010110011000 "
b100011001101111 $
#1490000
b1000011010111 !
b10001010011000 "
b11001101101111 $
#1500000
b1000011010111 !
b1000111001001 "
b10001010100000 $
#1510000
b1000001110111010 !
b1000111001001 "
b1001010110000011 $
#1520000
b1010111000110 !
b1000111001001 "
b10011110001111 $
#1530000
b1010101110100 !
b10100001000 "
b1101001111100 $
#1540000
b10101100000110 !
b10010001100011 "
b100111101101001 $
#1550000
b10101100000110 !
b10010001100011 "
#1560000
b1011111001000 !
b11001011100 "
b1111000100100 $
#1570000
b1011111001000 !
b11001011100 "
#1580000
b11000010110001 !
b11001011100 "
b11011100001101 $
#1590000
b11000010110001 !
b11001011100 "
#1600000
b1010100011010 !
b1100010001 "
b1100000101011 $
#1610000
b1010100011010 !
b1100010001 "
#1620000
b101001010111 !
b1100010001 "
b110101101000 $
#1630000
b10011000001 !
b11010001000100 "
b11100100000101 $
#1640000
b111101000101 !
b10001000011100 "
b11000101100001 $
#1650000
b111101000101 !
b10100010111010 "
b11011111111111 $
#1660000
b111101000101 !
b10100010111010 "
#1670000
b111101000101 !
b10100010111010 "
#1680000
b10000010110 !
b10100010111010 "
b10110011010000 $
#1690000
b10101100011 !
b100001100010 "
b110111000101 $
#1700000
b1000000011011 !
b100001011101001 "
b101001100000100 $
#1710000
b1000000011011 !
b100001011101001 "
#1720000
b11110101000000 !
b100001011101001 "
b1000000000101001 $
#1730000
b101110110100 !
b11110010010 "
b1001101000110 $
#1740000
b1010010000110 !
b11001001010011 "
b100011011011001 $
#1750000
b1010010000110 !
b1000111000010 "
b10011001001000 $
#1760000
b10110110110 !
b1000111000010 "
b1011101111000 $
#1770000
b101011110001 !
b1011110000011 "
b10001001110100 $
#1780000
b101011110001 !
b1011110000011 "
#1790000
b101011110001 !
b1011110000011 "
#1800000
b101011110001 !
b1100111110111 "
b10010011101000 $
#1810000
b101101001101 !
b100101000 "
b110001110101 $
#1820000
b101101001101 !
b100101000 "
#1830000
b101101001101 !
b100101000 "
#1840000
b11001000101001 !
b11000001111 "
b11100000111000 $
#1850000
b11100001101011 !
b11000001111 "
b11111001111010 $
#1860000
b11100001101011 !
b10010011111101 "
b101110101101000 $
#1870000
b11100001101011 !
b10010011111101 "
#1880000
b1100010011011 !
b10010011111101 "
b11110110011000 $
#1890000
b1100010011011 !
b110011110001100 "
b1000000000100111 $
#1900000
b1100010011011 !
b110011110001100 "
#1910000
b10010000001100 !
b110011110001100 "
b1000101110011000 $
#1920000
b1101111000010 !
b110011110001100 "
b1000001101001110 $
#1930000
b100101101100100 !
b10001011100110 "
b110111001001010 $
#1940000
b100001111101 !
b1111110101100 "
b10100000101001 $
#1950000
b100001111101 !
b1111110101100 "
#1960000
b100001111101 !
b1010100110001110 "
b1011001000001011 $
#1970000
b100001111101 !
b1001111000001101 "
b1010011010001010 $
#1980000
b100111101110101 !
b100101110111001 "
b1001101100101110 $
#1990000
b110000010101 !
b10001101011111 "
b10111101110100 $
#2000000
b110000010101 !
b101110111100 "
b1011111010001 $
#2010000
b110000010101 !
b11010010101 "
b1001010101010 $
#2020000
b1000111100101011 !
b11110111100 "
b1001011011100111 $
#2030000
b1000111100101011 !
b1001000101001 "
b1010000101010100 $
#2040000
b1000111100101011 !
b11010110000 "
b1001010111011011 $
#2050000
b1000111100101011 !
b10001000101111 "
b1011000101011010 $
#2060000
b111101010011 !
b111110000111 "
b1111011011010 $
#2070000
b111101010011 !
b11111100 "
b1000001001111 $
#2080000
b101000110010 !
b100000001010 "
b1001000111100 $
#2090000
b1100111001000 !
b10001010010001 "
b11110001011001 $
#2100000
b1100111001000 !
b111010110110 "
b10100001111110 $
#2110000
b1100111001000 !
b111010110110 "
#2120000
b11010101100 !
b1000001001000 "
b1011011110100 $
#2130000
b101111100010 !
b1000001001000 "
b1110000101010 $
#2140000
b101111100010 !
b100000001001 "
b1001111101011 $
#2150000
b101111100010 !
b1000011110110 "
b1110011011000 $
#2160000
b101111100010 !
b111011001110 "
b1101010110000 $
#2170000
b101111100010 !
b111011001110 "
#2180000
b11010100000 !
b10101100111 "
b110000000111 $
#2190000
b11010100000 !
b10101100111 "
#2200000
b101110010001101 !
b1000010101000 "
b110110100110101 $
#2210000
b101110010001101 !
b101000110100010 "
b1010111000101111 $
#2220000
b111101011110 !
b10111011101 "
b1010100111011 $
#2230000
b110011101 !
b100001011011101 "
b100010001111010 $
#2240000
b100000100111101 !
b11101000000000 "
b111101100111101 $
#2250000
b10000111101110 !
b11101000000000 "
b101101111101110 $
#2260000
b10000111101110 !
b11000011000100 "
b101001010110010 $
#2270000
b10101101011 !
b11111000010110 "
b100001110000001 $
#2280000
b1001101 !
b10101101110010 "
b10101110111111 $
#2290000
b1001101 !
b10101001001100 "
b10101010011001 $
#2300000
b1001101 !
b100001011000001 "
b100001100001110 $
#2310000
b101110111101 !
b100001011000001 "
b100111001111110 $
#2320000
b101101111110 !
b10011101110010 "
b11001011110000 $
#2330000
b101101111110 !
b111000000000111 "
b111101110000101 $
#2340000
b10101110001110 !
b1101011010110 "
b100011001100100 $
#2350000
b10101110001110 !
b1101011010110 "
#2360000
b1011010010011 !
b1101011010110 "
b11000101101001 $
#2370000
b10001010101010 !
b1101011010110 "
b11110110000000 $
#2380000
b10001010101010 !
b1101011010110 "
#2390000
b10001010101010 !
b10000010000100 "
b100001100101110 $
#2400000
b11000001010 !
b10000010000100 "
b10011010001110 $
#2410000
b11000001010 !
b10000010000100 "
#2420000
b1010101011 !
b10000010000100 "
b10001100101111 $
#2430000
b110100100100 !
b101101111100 "
b1100010100000 $
#2440000
b11000111 !
b1011001000 "
b1110001111 $
#2450000
b11000111 !
b1011001000 "
#2460000
b1000100100011 !
b1011001000 "
b1001111101011 $
#2470000
b1000100100011 !
b1010011010000 "
b10010111110011 $
#2480000
b1111110000000 !
b101110100001111 "
b111110010001111 $
#2490000
b1010101001 !
b101110100001111 "
b101111110111000 $
#2500000
b1010101001 !
b100101100100 "
b110000001101 $
#2510000
b1000010011011 !
b100100000001110 "
b101100010101001 $
#2520000
b1010100101000 !
b100100000001110 "
b101110100110110 $
#2530000
b10100011011101 !
b1000010010001 "
b11100101101110 $
#2540000
b10100011011101 !
b1110100001000 "
b100010111100101 $
#2550000
b10100011011101 !
b110001100 "
b10101001101001 $
#2560000
b110001111000 !
b110001100 "
b111000000100 $
#2570000
b100110111000001 !
b110001100 "
b100111101001101 $
#2580000
b100110111000001 !
b110001100 "
#2590000
b10111011001100 !
b110001100 "
b11000001011000 $
#2600000
b11100000010001 !
b110001100 "
b11100110011101 $
#2610000
b1101110001 !
b110001100 "
b10011111101 $
#2620000
b1101110001 !
b111110000101 "
b1001011110110 $
#2630000
b100110010100010 !
b111110000101 "
b101110000100111 $
#2640000
b100110010100010 !
b111110000101 "
#2650000
b101100010011 !
b101000100111010 "
b101110001001101 $
#2660000
b1001110010011 !
b101000100111010 "
b110010011001101 $
#2670000
b110110001111 !
b101000100111010 "
b101111011001001 $
#2680000
b10111110101100 !
b101000100111010 "
b1000000011100110 $
#2690000
b1000101100 !
b1010011110000 "
b1011100011100 $
#2700000
b101011111110 !
b110100001111 "
b1100000001101 $
#2710000
b101011111110 !
b110110001000 "
b1100010000110 $
#2720000
b101011111110 !
b1011100001100 "
b10001000001010 $
#2730000
b101011111110 !
b1011100001100 "
#2740000
b101011111110 !
b1011100001100 "
#2750000
b10011001010 !
b1011100001100 "
b1101111010110 $
#2760000
b10011001010 !
b100111111100111 "
b101010010110001 $
#2770000
b10011001010 !
b110110110011011 "
b111001001100101 $
#2780000
b10011001010 !
b111000001101 "
b1001011010111 $
#2790000
b10011001010 !
b10101011011100 "
b10111110100110 $
#2800000
b11000010001 !
b110011101110001 "
b110110110000010 $
#2810000
b11000010001 !
b1011111101111 "
b1111000000000 $
#2820000
b11010100100100 !
b1100101000011 "
b100111001100111 $
#2830000
b10101001110100 !
b1100101000011 "
b100001110110111 $
#2840000
b10010000100 !
b100110101000 "
b111000101100 $
#2850000
b10010000100 !
b100110101000 "
#2860000
b10010000100 !
b1111010001101 "
b10001100010001 $
#2870000
b10010000100 !
b1111010001101 "
#2880000
b11100000000010 !
b10110000101100 "
b110010000101110 $
#2890000
b1010101111000 !
b1111001011111 "
b11001111010111 $
#2900000
b1010101111000 !
b11011000111000 "
b100101110110000 $
#2910000
b11110100001 !
b11011000111000 "
b11110111011001 $
#2920000
b10001110000001 !
b10001000101101 "
b100010110101110 $
#2930000
b101100111000111 !
b10001000101101 "
b111101111110100 $
#2940000
b101100101011100 !
b10101010000000 "
b1000001111011100 $
#2950000
b101100101011100 !
b11101001010 "
b110000010100110 $
#2960000
b101100101011100 !
b10010011101001 "
b111111001000101 $
#2970000
b101100101011100 !
b10010011101001 "
#2980000
b1101011111110 !
b11100110011 "
b10001000110001 $
#2990000
b111101001111 !
b11100110011 "
b1011010000010 $
#3000000
b111101001111 !
b11100110011 "
#3010000
b111101001111 !
b1001010000010 "
b10000111010001 $
#3020000
b110010110100 !
b1110111110100 "
b10101010101000 $
#3030000
b110111 !
b1110001100100 "
b1110010011011 $
#3040000
b110111 !
b1000001101010 "
b1000010100001 $
#3050000
b1001110000110 !
b1100001111100 "
b10110000000010 $
#3060000
b10110000101 !
b10110101100001 "
b11001011100110 $
#3070000
b111111010000 !
b101101001101 "
b1101100011101 $
#3080000
b111111010000 !
b11101000000001 "
b100100111010001 $
#3090000
b111011100011 !
b11101000000001 "
b100100011100100 $
#3100000
b11111011110001 !
b11101000000001 "
b111100011110010 $
#3110000
b11111011110001 !
b10010001011000 "
b110001101001001 $
#3120000
b11111011110001 !
b10010001011000 "
#3130000
b11111011110001 !
b11101010110 "
b100011001000111 $
#3140000
b10110011001100 !
b11101010110 "
b11010000100010 $
#3150000
b110001101001 !
b11101010110 "
b1001110111111 $
#3160000
b110001101001 !
b10011101111 "
b1000101011000 $
#3170000
b110001101001 !
b1011000000000 "
b10001001101001 $
#3180000
b110001101001 !
b10100100100 "
b1000110001101 $
#3190000
b110001101001 !
b10100100100 "
#3200000
b110000010111111 !
b10100100100 "
b110010111100011 $
#3210000
b11001100000110 !
b10100100100 "
b11100000101010 $
#3220000
b11001100000110 !
b10100100100 "
#3230000
b11001100000110 !
b10100100100 "
#3240000
b100011000110 !
b11001110 "
b100110010100 $
#3250000
b101000001011011 !
b11001110 "
b101000100101001 $
#3260000
b1100010011 !
b101100100111 "
b111000111010 $
#3270000
b1100010011 !
b101100100111 "
#3280000
b111101000100 !
b110110111101110 "
b111110100110010 $
#3290000
b100100101000001 !
b110110111101110 "
b1011011100101111 $
#3300000
b100100101000001 !
b110110 "
b100100101110111 $
#3310000
b100100101000001 !
b110110 "
#3320000
b100100101000001 !
b110110 "
#3330000
b10100001110100 !
b10000010111100 "
b100100100110000 $
#3340000
b110011100011 !
b11000100 "
b110110100111 $
#3350000
b110011100011 !
b11000100 "
#3360000
b101100010100 !
b11000100 "
b101111011000 $
#3370000
b1011100101100 !
b100100101000 "
b10000001010100 $
#3380000
b1011100101100 !
b11001110001 "
b1110110011101 $
#3390000
b1011100101100 !
b11001110001 "
#3400000
b100010100 !
b11110 "
b100110010 $
#3410000
b101111000110 !
b11010000010 "
b1001001001000 $
#3420000
b101111000110 !
b1101010010001 "
b10011001010111 $
#3430000
b1001110011111 !
b10010011101 "
b1100000111100 $
#3440000
b100100010010100 !
b1010011001011 "
b101110101011111 $
#3450000
b100100010010100 !
b10100 "
b100100010101000 $
#3460000
b1111010111110 !
b11100110101 "
b10010111110011 $
#3470000
b1111010111110 !
b1011001011001 "
b11010100010111 $
#3480000
b10111100010000 !
b10101110110000 "
b101101011000000 $
#3490000
b11000100110 !
b1000101100001 "
b1011110000111 $
#3500000
b11000100110 !
b1000101100001 "
#3510000
b11000100110 !
b1000101100001 "
#3520000
b10011111100000 !
b101101010111101 "
b1000001010011101 $
#3530000
b10011111100000 !
b101101010111101 "
#3540000
b1100111011011 !
b101101010111101 "
b111010010011000 $
#3550000
b1011100000011 !
b1111001001010 "
b11010101001101 $
#3560000
b1011100000011 !
b1000101011101 "
b10100001100000 $
#3570000
b1011100000011 !
b1101001111011 "
b11000101111110 $
#3580000
b11011001101111 !
b1101001111011 "
b101000011101010 $
#3590000
b11011001101111 !
b1100010101000 "
b100111100010111 $
#3600000
b10101000000100 !
b1100010101000 "
b100001010101100 $
#3610000
b10000000011101 !
b1100010101000 "
b11100011000101 $
#3620000
b101100001110 !
b10001110100011 "
b10111010110001 $
#3630000
b1110110111010 !
b10001110100011 "
b100000101011101 $
#3640000
b1110110111010 !
b10001110100011 "
#3650000
b1110110111010 !
b10001110100011 "
#3660000
b1110110111010 !
b111110101101 "
b10110101100111 $
#3670000
b1110110111010 !
b1101010 "
b1111000100100 $
#3680000
b11101000111000 !
b1101010 "
b11101010100010 $
#3690000
b11101000111000 !
b1101010 "
#3700000
b1010000100110 !
b11000000101 "
b1101000101011 $
#3710000
b1001110010 !
b10010100000100 "
b10011101110110 $
#3720000
b1001110010 !
b10010100000100 "
#3730000
b1001110010 !
b10010100000100 "
#3740000
b1001110010 !
b10010100000100 "
#3750000
b10011100100 !
b10010100000100 "
b10100111101000 $
#3760000
b101100110111000 !
b10010100000100 "
b111111010111100 $
#3770000
b101100110111000 !
b10010100000100 "
#3780000
b1011111000000 !
b10010100000100 "
b11110011000100 $
#3790000
b1011111000000 !
b100010011100001 "
b101110010100001 $
#3800000
b1011111000000 !
b1111000110110 "
b11010111110110 $
#3810000
b1011111000000 !
b1111000110110 "
#3820000
b1011111000000 !
b1111000110110 "
#3830000
b1011111000000 !
b1111000110110 "
#3840000
b100100001100 !
b101010011111110 "
b101111000001010 $
#3850000
b10011100011010 !
b110000011000101 "
b1000011111011111 $
#3860000
b10011001100100 !
b110000011000101 "
b1000011100101001 $
#3870000
b1011011100111 !
b110000011000101 "
b111011110101100 $
#3880000
b1011011100111 !
b1101010000110 "
b11000101101101 $
#3890000
b1011011100111 !
b1101010000110 "
#3900000
b1011011100111 !
b1101010000110 "
#3910000
b1011011100111 !
b1101010000110 "
#3920000
b1000000011100 !
b11100011111 "
b1011100111011 $
#3930000
b11010101001001 !
b11100011111 "
b11110001101000 $
#3940000
b111010110000 !
b11100011111 "
b1010111001111 $
#3950000
b110000110000110 !
b11100011111 "
b110100010100101 $
#3960000
b110000110000110 !
b11001011000100 "
b1001010001001010 $
#3970000
b110000110000110 !
b111111 "
b110000111000101 $
#3980000
b110000110000110 !
b1110100111111 "
b111111011000101 $
#3990000
b1000110110110 !
b10101111010 "
b1011100110000 $
#4000000
b1000110110110 !
b10101111010 "
#4010000
b11011000010100 !
b10010011010010 "
b101101011100110 $
#4020000
b11011000010100 !
b10110110111100 "
b110001111010000 $
#4030000
b11011000010100 !
b10010010001110 "
b101101010100010 $
#4040000
b101101001111 !
b10010010001110 "
b10111111011101 $
#4050000
b111100101111 !
b10010010001110 "
b11001110111101 $
#4060000
b111100101111 !
b1100100100101 "
b10100001010100 $
#4070000
b111100101111 !
b1100100100101 "
#4080000
b111100101111 !
b1000101010110 "
b10000010000101 $
#4090000
b10101110111110 !
b1000101010110 "
b11110100010100 $
#4100000
b111011111010 !
b1000101011001 "
b10000001010011 $
#4110000
b111011111010 !
b1000101011001 "
#4120000
b111011111010 !
b110110100101 "
b1110010011111 $
#4130000
b111011111010 !
b110110100101 "
#4140000
b111011111010 !
b110110100101 "
#4150000
b110001111101 !
b111011011101 "
b1101101011010 $
#4160000
b110001111101 !
b111011011101 "
#4170000
b110001111101 !
b1100111000101 "
b10011001000010 $
#4180000
b1010001111011 !
b10101100011 "
b1100111011110 $
#4190000
b1010001111011 !
b10101100011 "
#4200000
b1010001111011 !
b10101100011 "
#4210000
b100000111 !
b10101100011 "
b11001101010 $
#4220000
b100100101111110 !
b10101100011 "
b100111011100001 $
#4230000
b100100101111110 !
b10101100011 "
#4240000
b100100101111110 !
b10101100011 "
#4250000
b101010110100100 !
b10101100011 "
b101101100000111 $
#4260000
b10101011000000 !
b10101100011 "
b11000000100011 $
#4270000
b11010001 !
b111000 "
b100001001 $
#4280000
b11010001 !
b10000110111101 "
b10001010001110 $
#4290000
b1111010001000 !
b10000110111101 "
b100000001000101 $
#4300000
b1111010001000 !
b10000110111101 "
#4310000
b1111010001000 !
b10000110111101 "
#4320000
b1111010001000 !
b10000110111101 "
#4330000
b1111010001000 !
b10000110111101 "
#4340000
b1111010001000 !
b10000110111101 "
#4350000
b1111010001000 !
b11111110011100 "
b101111000100100 $
#4360000
b1111010001000 !
b11111110011100 "
#4370000
b100011100000101 !
b11111110011100 "
b1000011010100001 $
#4380000
b10000011011111 !
b1011001111010 "
b11011101011001 $
#4390000
b10000011011111 !
b1011001111010 "
#4400000
b10000011011111 !
b10101100010100 "
b100101111110011 $
#4410000
b10000011011111 !
b10101100010100 "
#4420000
b11110010100 !
b10101100010100 "
b11001010101000 $
#4430000
b1011111 !
b10101100010100 "
b10101101110011 $
#4440000
b10001110000111 !
b1111000 "
b10001111111111 $
#4450000
b100000100001 !
b1111000 "
b100010011001 $
#4460000
b1110000101010 !
b1111000 "
b1110010100010 $
#4470000
b1110000101010 !
b1111000 "
#4480000
b111101001110 !
b100100110000010 "
b101100011010000 $
#4490000
b111101001110 !
b11000101010 "
b1010101111000 $
#4500000
b10111100100 !
b10101011101110 "
b11000011010010 $
