old_src/full_adder.v
`timescale 1ns / 1ps

module full_adder(
    input a, 
    input b, 
    input cin, 
    output sum, 
    output cout
);

assign sum = a ^ b ^ cin;
assign cout = (a & b) | (b & cin) | (a & cin);

endmodule

old_src/rca_8bit.v
`timescale 1ns / 1ps

module rca_8bit(
    input [7:0] a,
    input [7:0] b,
    input cin,
    output [7:0] sum,
    output cout
);
    
    wire [6:0] c;

    full_adder fa0 (a[0], b[0], cin, sum[0], c[0]);
    full_adder fa1 (a[1], b[1], c[0], sum[1], c[1]);
    full_adder fa2 (a[2], b[2], c[1], sum[2], c[2]);
    full_adder fa3 (a[3], b[3], c[2], sum[3], c[3]);
    full_adder fa4 (a[4], b[4], c[3], sum[4], c[4]);
    full_adder fa5 (a[5], b[5], c[4], sum[5], c[5]);
    full_adder fa6 (a[6], b[6], c[5], sum[6], c[6]);
    full_adder fa7 (a[7], b[7], c[6], sum[7], cout);

endmodule

old_src/rca_16bit.v
`timescale 1ns / 1ps

module rca_16bit(
    input [15:0] a,
    input [15:0] b,
    input cin,
    output [15:0] sum,
    output cout
);
    
    wire c8;
    
    rca_8bit low (a[7:0], b[7:0], cin, sum[7:0], c8);
    rca_8bit high (a[15:8], b[15:8], c8, sum[15:8], cout);

endmodule

old_src/sim_rca_16bit_normal.v
`timescale 1ns/1ps

module sim_rca_16bit_normal;

    reg  [15:0] a, b;
    reg cin;
    wire [15:0] sum;
    wire cout;

    // Arquivos
    integer in_file;
    integer out_file;
    integer r;
    
    rca_16bit DUT (
        .a(a),
        .b(b),
        .cin(cin),
        .sum(sum),
        .cout(cout)
    );

        // Caminhos de arquivo de entrada e saída
    reg [1023:0] input_file  = "/home/tiago/energetic_efficiency/data/16_normal.txt";
    reg [1023:0] output_file = "/home/tiago/energetic_efficiency/results/rca_16bit_normal.txt";
//     
    initial begin
        // Abre arquivos
        in_file  = $fopen(input_file, "r");
        out_file = $fopen(output_file, "w");

        if(in_file == 0) begin
            $display("Erro ao abrir arquivo de entrada: %s", input_file);
            $finish;
        end
        if(out_file == 0) begin
            $display("Erro ao abrir arquivo de saída: %s", output_file);
            $finish;
        end

        $display("Simulação iniciada: %s -> %s", input_file, output_file);

        // fixa o carry-in
        cin = 0;

        // Processamento Sequencial Sem Clock Rápido
        while (!$feof(in_file)) begin
            // 1. Lê os dados do arquivo
            r = $fscanf(in_file, "%h %h\n", a, b);
            
            // 2. Aguarda um tempo para a lógica combinacional estabilizar
            // 10ns é mais que suficiente para um RCA de 16 bits na Spartan-7
            #10; 
            
            // 3. Grava a entrada E a saída resultante na mesma linha
            $fwrite(out_file, "%h %h %b %h %b\n", a, b, cin, sum, cout);
        end

        $fclose(in_file);
        $fclose(out_file);

        $display("Simulação concluída.");
        $finish;
    end

endmodule

results/sim_rca_16bit_normal.vcd
$date
   Wed Mar 18 13:41:15 2026
$end
$version
  2022.1
$end
$timescale
  1ps
$end
$scope module sim_rca_16bit_normal $end
$var reg 16 ! a [15:0] $end
$var reg 16 " b [15:0] $end
$var reg 1 # cin $end
$var wire 16 $ sum [15:0] $end
$var wire 1 % cout $end
$var integer 32 & in_file [31:0] $end
$var integer 32 ' out_file [31:0] $end
$var integer 32 ( r [31:0] $end
$var reg 1024 ) input_file [1023:0] $end
$var reg 1024 * output_file [1023:0] $end
$upscope $end
$enddefinitions $end
#0
$dumpvars
b110110011110101 !
b111100010111001 "
0#
b1110010110101110 $
0%
b11111111111111111011000111100000 &
b11111111111111111011000111100001 '
b10 (
b1011110110100001101111011011010110010100101111011101000110100101100001011001110110111100101111011001010110111001100101011100100110011101100101011101000110100101100011010111110110010101100110011001100110100101100011011010010110010101101110011000110111100100101111011001000110000101110100011000010010111100110001001101100101111101101110011011110111001001101101011000010110110000101110011101000111100001110100 )
b101111011010000110111101101101011001010010111101110100011010010110000101100111011011110010111101100101011011100110010101110010011001110110010101110100011010010110001101011111011001010110011001100110011010010110001101101001011001010110111001100011011110010010111101110010011001010111001101110101011011000111010001110011001011110111001001100011011000010101111100110001001101100110001001101001011101000101111101101110011011110111001001101101011000010110110000101110011101000111100001110100 *
$end
#10000
b110110011110101 !
b111100010111001 "
#20000
b110110011110101 !
b111100010111001 "
#30000
b110100101100111 !
b110101011111010 "
b1101010001100001 $
#40000
b1001010000100001 !
b110101011111010 "
b1111111100011011 $
0%
#50000
b1001010000100001 !
b110101011111010 "
#60000
b1001010000100001 !
b110101011111010 "
#70000
b1110111000101110 !
b110101011111010 "
b101100100101000 $
1%
#80000
b101011011101110 !
b110101011111010 "
b1100000111101000 $
0%
#90000
b101011011101110 !
b110101011111010 "
#100000
b101011011101110 !
b110101011111010 "
#110000
b1000101010010001 !
b110101011111010 "
b1111010110001011 $
0%
#120000
b1000101010010001 !
b110101011111010 "
#130000
b1010111100100101 !
b1010111000000001 "
b101110100100110 $
1%
#140000
b1010111100100101 !
b1010111000000001 "
#150000
b1010111100100101 !
b1100110101001100 "
b111110001110001 $
#160000
b100001011000110 !
b1100110101001100 "
b1000000010010 $
#170000
b1000001100010111 !
b1100110101001100 "
b101000001100011 $
#180000
b1000001100010111 !
b1001001110110100 "
b1011011001011 $
#190000
b1000001100010111 !
b101111110100111 "
b1110001010111110 $
0%
#200000
b1000001100010111 !
b1000101110010010 "
b111010101001 $
1%
#210000
b1001000011001011 !
b1000101110010010 "
b1110001011101 $
#220000
b1001000011001011 !
b1001011010111101 "
b10011110001000 $
#230000
b1001000011001011 !
b1001011010111101 "
#240000
b1001000011001011 !
b101111100111000 "
b1111000000000011 $
0%
#250000
b1001000011001011 !
b101111100111000 "
#260000
b1001000011001011 !
b1001001001110010 "
b10001100111101 $
1%
#270000
b1001000011001011 !
b111001111000110 "
b10010010001 $
#280000
b1001000011001011 !
b1010000101011001 "
b11001000100100 $
#290000
b1001000011001011 !
b1000110100101011 "
b1110111110110 $
#300000
b111000110101001 !
b1011010101101010 "
b10011100010011 $
#310000
b1000100100100010 !
b1011010101101010 "
b11111010001100 $
#320000
b100010011000010 !
b110010100001010 "
b1010100111001100 $
0%
#330000
b111111011010101 !
b111000001010001 "
b1110111100100110 $
#340000
b110000111101100 !
b101010001011010 "
b1011011001000110 $
#350000
b1000110011011100 !
b101010001011010 "
b1110000100110110 $
#360000
b1000110011011100 !
b101010001011010 "
#370000
b1000110011011100 !
b101110011111101 "
b1110100111011001 $
#380000
b111000110000101 !
b1010011001011100 "
b1011111100001 $
1%
#390000
b10111111000001 !
b1010011001011100 "
b1101011000011101 $
0%
#400000
b10111111000001 !
b1010011001011100 "
#410000
b10111111000001 !
b1000011101011000 "
b1011011100011001 $
#420000
b110000111111110 !
b111011011100100 "
b1101100011100010 $
#430000
b1000100001000001 !
b111011011100100 "
b1111111100100101 $
0%
#440000
b1000011010110111 !
b111000101101110 "
b1111100000100101 $
#450000
b1000011010110111 !
b111000101101110 "
#460000
b110111111001000 !
b111000101101110 "
b1110000100110110 $
#470000
b110111111001000 !
b1001000110001111 "
b101010111 $
1%
#480000
b110101111011100 !
b1000110011111100 "
b1111100011011000 $
0%
#490000
b110101001001110 !
b1000001010110000 "
b1110110011111110 $
#500000
b1001010110011111 !
b1001000001100001 "
b10011000000000 $
1%
#510000
b1001010110011111 !
b1001000001100001 "
#520000
b101001000101010 !
b111100000000110 "
b1100101000110000 $
0%
#530000
b101001000101010 !
b111100000000110 "
#540000
b101001000101010 !
b111100000000110 "
#550000
b1011110100110000 !
b111011101000000 "
b11010001110000 $
1%
#560000
b1100111101100110 !
b111011101000000 "
b100011010100110 $
#570000
b1011000010011011 !
b1000000111001100 "
b11001001100111 $
#580000
b1011000010011011 !
b1000000111001100 "
#590000
b1011000010011011 !
b1000000111001100 "
#600000
b110011110100110 !
b1010111111000110 "
b1011101101100 $
#610000
b1100011100101111 !
b110010111010001 "
b10110100000000 $
#620000
b1000110001111101 !
b110010111010001 "
b1111001001001110 $
0%
#630000
b1010111001110010 !
b110010111010001 "
b1010001000011 $
1%
#640000
b111111001011011 !
b110010111010001 "
b1110010000101100 $
0%
#650000
b1001000001011101 !
b110010111010001 "
b1111011000101110 $
0%
#660000
b1001000001011101 !
b100000110101100 "
b1101001000001001 $
#670000
b1001000001011101 !
b100000110101100 "
#680000
b1001000001011101 !
b110011000100010 "
b1111011001111111 $
#690000
b1001000001011101 !
b1010111101101010 "
b11111111000111 $
1%
#700000
b1001000001011101 !
b1010111101101010 "
#710000
b1001000001011101 !
b1010111101101010 "
#720000
b1001000001011101 !
b1101000110010010 "
b110000111101111 $
#730000
b1001000001011101 !
b1001011111101001 "
b10100001000110 $
#740000
b1001001100010110 !
b1001011111101001 "
b10101011111111 $
#750000
b1001001100010110 !
b1001011111101001 "
#760000
b111011101010001 !
b1000010101010001 "
b1111110010100010 $
0%
#770000
b111011101010001 !
b1000010101010001 "
#780000
b1000011000011000 !
b110110100011010 "
b1111001100110010 $
#790000
b1000011000011000 !
b110110100011010 "
#800000
b1000011000011000 !
b110110100011010 "
#810000
b1000011000011000 !
b110110100011010 "
#820000
b100110100111011 !
b100000110001101 "
b1000111011001000 $
#830000
b100110100111011 !
b101110011101101 "
b1010101000101000 $
#840000
b100110100111011 !
b101110011101101 "
#850000
b101001010011111 !
b101110011101101 "
b1010111110001100 $
#860000
b1001001111110101 !
b1000100000001110 "
b1110000000011 $
1%
#870000
b1001001111110101 !
b1000100000001110 "
#880000
b111000001110111 !
b110001101010100 "
b1101001111001011 $
0%
#890000
b111000001110111 !
b110101010111111 "
b1101101100110110 $
#900000
b111000001110111 !
b1000110011101100 "
b1111110101100011 $
#910000
b111000001010101 !
b101010011000000 "
b1100010100010101 $
#920000
b11010010100101 !
b101010011000000 "
b1000100101100101 $
#930000
b111110110111101 !
b110010001101111 "
b1110001000101100 $
#940000
b111110110111101 !
b110010001101111 "
#950000
b111110110111101 !
b110010001101111 "
#960000
b110100100011000 !
b110010001101111 "
b1100110110000111 $
#970000
b110100100011000 !
b110010001101111 "
#980000
b110100100011000 !
b110010001101111 "
#990000
b11101110110000 !
b110010001101111 "
b1010000000011111 $
#1000000
b11101110110000 !
b1000011001100011 "
b1100001000010011 $
#1010000
b1001101100101001 !
b1001001000101011 "
b10110101010100 $
1%
#1020000
b1001101100101001 !
b110100001010100 "
b1101111101 $
#1030000
b101010100011110 !
b110100001010100 "
b1011110101110010 $
0%
#1040000
b1001110011001001 !
b110100001010100 "
b10100011101 $
1%
#1050000
b1001110011001001 !
b111000111110110 "
b111010111111 $
#1060000
b101110000101001 !
b1011110010101001 "
b1100011010010 $
#1070000
b111101010001011 !
b1000010000011101 "
b1111111010101000 $
0%
#1080000
b111101010001011 !
b1000010000011101 "
#1090000
b111101010001011 !
b1000010000011101 "
#1100000
b111101010001011 !
b1000010100110000 "
b1111111110111011 $
#1110000
b1001110110110000 !
b1000010100110000 "
b10001011100000 $
1%
#1120000
b1001001110101000 !
b1000010100110000 "
b1100011011000 $
#1130000
b1000010001111010 !
b1011101011011011 "
b11111101010101 $
#1140000
b1000010001111010 !
b1011101011011011 "
#1150000
b101011001101100 !
b1011101011011011 "
b1000101000111 $
1%
#1160000
b110110111010001 !
b1000100100000101 "
b1111011011010110 $
0%
#1170000
b1000001101011111 !
b101011001110001 "
b1101100111010000 $
#1180000
b1000001101011111 !
b1000100101110000 "
b110011001111 $
1%
#1190000
b111100101100011 !
b110101011000001 "
b1110010000100100 $
0%
#1200000
b1001101110101011 !
b101110011010001 "
b1111100001111100 $
#1210000
b110001110111000 !
b101110011010001 "
b1100000010001001 $
#1220000
b110001110111000 !
b110000001101101 "
b1100010000100101 $
#1230000
b110001011001010 !
b111000110110001 "
b1101010001111011 $
#1240000
b110001011001010 !
b111000110110001 "
#1250000
b110001011001010 !
b111000110110001 "
#1260000
b1010011011011101 !
b110101000010000 "
b1000011101101 $
1%
#1270000
b111010110100001 !
b110101000010000 "
b1101111110110001 $
0%
#1280000
b1010011111001010 !
b1010010001000100 "
b100110000001110 $
1%
#1290000
b1010011111001010 !
b110100000110010 "
b111111111100 $
#1300000
b1010011111001010 !
b101001110011110 "
b1111101101101000 $
0%
#1310000
b1001111110110011 !
b101001110011110 "
b1111001101010001 $
#1320000
b1001111110110011 !
b1000111111100100 "
b10111110010111 $
1%
#1330000
b111111110001011 !
b110111101011101 "
b1110111011101000 $
0%
#1340000
b111111110001011 !
b110111101011101 "
#1350000
b111111110001011 !
b11100111111010 "
b1011100110000101 $
#1360000
b111111110001011 !
b11100111111010 "
#1370000
b111111110001011 !
b1010111100110101 "
b10111011000000 $
1%
#1380000
b111111110001011 !
b1010111100110101 "
#1390000
b111111110001011 !
b1010111100110101 "
#1400000
b111111110001011 !
b101011001001000 "
b1101010111010011 $
0%
#1410000
b1001111100010001 !
b110101101111101 "
b101010001110 $
1%
#1420000
b100101000101110 !
b110101101111101 "
b1011010110101011 $
0%
#1430000
b1001010011010111 !
b111001100001010 "
b11111100001 $
1%
#1440000
b100101100110100 !
b111001100001010 "
b1011111000111110 $
0%
#1450000
b1000010011100001 !
b100111110101011 "
b1101010010001100 $
#1460000
b1001110001101010 !
b101110101101110 "
b1111100111011000 $
#1470000
b111111011011100 !
b101110101101110 "
b1101110001001010 $
#1480000
b101100100101101 !
b101110101101110 "
b1011011010011011 $
#1490000
b101100100101101 !
b101110101101110 "
#1500000
b110111011001100 !
b101110101101110 "
b1100110000111010 $
#1510000
b110111011001100 !
b101110101101110 "
#1520000
b110111011001100 !
b1001001100100100 "
b111110000 $
1%
#1530000
b1000101101111101 !
b1001001110100000 "
b1111100011101 $
#1540000
b1000101101111101 !
b110100000100110 "
b1111001110100011 $
0%
#1550000
b1001100001100000 !
b110100000100110 "
b10000110 $
1%
#1560000
b1010000100100011 !
b110110010011010 "
b110110111101 $
#1570000
b1000101100100111 !
b110110010011010 "
b1111011111000001 $
0%
#1580000
b1000101100100111 !
b1000000111011011 "
b110100000010 $
1%
#1590000
b110011101100010 !
b111101101010000 "
b1110001010110010 $
0%
#1600000
b110010000010100 !
b111101101010000 "
b1101111101100100 $
#1610000
b110010000010100 !
b1011001001001111 "
b1011001100011 $
1%
#1620000
b110010000010100 !
b1011001001001111 "
#1630000
b110010000010100 !
b1011001001001111 "
#1640000
b110010000010100 !
b1011111101110110 "
b10001110001010 $
#1650000
b110010000010100 !
b1011111101110110 "
#1660000
b110010000010100 !
b1011111101110110 "
#1670000
b111000100111110 !
b1000111101010111 "
b10010101 $
1%
#1680000
b111000100111110 !
b1000111101010111 "
#1690000
b1000101001001110 !
b110000001101111 "
b1110101010111101 $
0%
#1700000
b111011001000101 !
b110000001101111 "
b1101011010110100 $
#1710000
b111011001000101 !
b110000001101111 "
#1720000
b1011110000011101 !
b110000001101111 "
b1110010001100 $
1%
#1730000
b1011110000011101 !
b110000001101111 "
#1740000
b1011110000011101 !
b110100000110001 "
b10010001001110 $
#1750000
b1001000001010010 !
b110100000110001 "
b1111100010000011 $
0%
#1760000
b1001000001010010 !
b110011001010000 "
b1111011010100010 $
#1770000
b1001000001010010 !
b1011011100001011 "
b100011101011101 $
1%
#1780000
b1001000001010010 !
b1000100011101100 "
b1100100111110 $
#1790000
b1001000001010010 !
b1000100011101100 "
#1800000
b1001000001010010 !
b1000100011101100 "
#1810000
b101111001011110 !
b1000100011101100 "
b1110011101001010 $
0%
#1820000
b100001111000010 !
b110001100110100 "
b1010011011110110 $
#1830000
b100001111000010 !
b110001100110100 "
#1840000
b100001111000010 !
b110001100110100 "
#1850000
b100001111000010 !
b110001100110100 "
#1860000
b101111111001111 !
b110001100110100 "
b1100001100000011 $
#1870000
b101111111001111 !
b111110100000101 "
b1101110011010100 $
#1880000
b101111111001111 !
b111000011100100 "
b1101000010110011 $
#1890000
b101111111001111 !
b111000011100100 "
#1900000
b101111111001111 !
b111011111100011 "
b1101011110110010 $
#1910000
b111101110011011 !
b111011111100011 "
b1111001101111110 $
#1920000
b1010110010100100 !
b111111110001101 "
b10110000110001 $
1%
#1930000
b1010110010100100 !
b110011101110111 "
b1010000011011 $
#1940000
b1010110010100100 !
b111101101011011 "
b10011111111111 $
#1950000
b1000011010010111 !
b111101101011011 "
b111110010 $
1%
#1960000
b1001001101110101 !
b111101101011011 "
b111011010000 $
#1970000
b1001111001010111 !
b111101101011011 "
b1100110110010 $
#1980000
b1001111001010111 !
b111101101011011 "
#1990000
b1000110000101010 !
b110110010001010 "
b1111100010110100 $
0%
#2000000
b1000110000101010 !
b110110010001010 "
#2010000
b100110001101001 !
b110110010001010 "
b1011100011110011 $
#2020000
b100110001101001 !
b101110001001010 "
b1010100010110011 $
#2030000
b1001101011001000 !
b111110100100101 "
b1011111101101 $
1%
#2040000
b111110101100001 !
b111110100100101 "
b1111101010000110 $
0%
#2050000
b101010010110001 !
b111110100100101 "
b1101000111010110 $
#2060000
b101010010110001 !
b111011011110010 "
b1100101110100011 $
#2070000
b101010010110001 !
b1000010011111000 "
b1101100110101001 $
#2080000
b101010010110001 !
b1000010011111000 "
#2090000
b1010010100110101 !
b1010111110010001 "
b101010011000110 $
1%
#2100000
b1001000010110100 !
b1010111110010001 "
b100000001000101 $
#2110000
b110011001100100 !
b1010111110010001 "
b1010111110101 $
#2120000
b110011001100100 !
b1010111110010001 "
#2130000
b110011001100100 !
b111101100100100 "
b1110000110001000 $
0%
#2140000
b110011001100100 !
b111101100100100 "
#2150000
b1110000110101110 !
b111101100100100 "
b101110011010010 $
1%
#2160000
b110001110100101 !
b111101100100100 "
b1101111011001001 $
0%
#2170000
b111010011000010 !
b111101100100100 "
b1110111111100110 $
#2180000
b101101001000001 !
b10111101111011 "
b1000100110111100 $
#2190000
b1010000101101111 !
b1001110011100011 "
b11111001010010 $
1%
#2200000
b111100010100100 !
b1011010000010110 "
b10110010111010 $
#2210000
b111100010100100 !
b110001011001110 "
b1101101101110010 $
0%
#2220000
b111100010100100 !
b110001011001110 "
#2230000
b111100010100100 !
b110001011001110 "
#2240000
b110111100111001 !
b110001011001110 "
b1101001000000111 $
#2250000
b111001110010011 !
b110001011001110 "
b1101011001100001 $
#2260000
b111001110010011 !
b101110110100000 "
b1101000100110011 $
#2270000
b111001110010011 !
b101110110100000 "
#2280000
b1000010100000011 !
b101011100100000 "
b1101110000100011 $
#2290000
b1010111000011111 !
b1000010101010110 "
b11001101110101 $
1%
#2300000
b1001010000011100 !
b1000010101010110 "
b1100101110010 $
#2310000
b1001010000011100 !
b1000010101010110 "
#2320000
b1001010000011100 !
b1000010101010110 "
#2330000
b1001110111101101 !
b1001101010101100 "
b11100010011001 $
#2340000
b1001110111101101 !
b1001101010101100 "
#2350000
b111011011111110 !
b110001001101000 "
b1101100101100110 $
0%
#2360000
b111011011111110 !
b110001001101000 "
#2370000
b111011011111110 !
b110001001101000 "
#2380000
b111011011111110 !
b110001100110110 "
b1101101000110100 $
#2390000
b111011011111110 !
b110111010011001 "
b1110010110010111 $
#2400000
b111011011111110 !
b1001011011110111 "
b110111110101 $
1%
#2410000
b1010001011000001 !
b110111000101111 "
b1000011110000 $
#2420000
b110111100010110 !
b1001101100100111 "
b101000111101 $
#2430000
b1000100000001110 !
b1001101100100111 "
b10001100110101 $
#2440000
b1000100000001110 !
b1000010100001001 "
b110100010111 $
#2450000
b1000100000001110 !
b1000010100001001 "
#2460000
b1000100000001110 !
b1001100010110100 "
b10000011000010 $
#2470000
b100101011101010 !
b101110010110000 "
b1010011110011010 $
0%
#2480000
b100101011101010 !
b1000000010101000 "
b1100101110010010 $
#2490000
b110010001110010 !
b1000000010101000 "
b1110010100011010 $
#2500000
b110100111100001 !
b101110000011011 "
b1100010111111100 $
#2510000
b110100111100001 !
b1010000100011111 "
b101100000000 $
1%
#2520000
b110100111100001 !
b1000110110000000 "
b1111011101100001 $
0%
#2530000
b111100101010010 !
b1001010001011010 "
b110110101100 $
1%
#2540000
b101111011100100 !
b1000111110100101 "
b1110111010001001 $
0%
#2550000
b100111101011011 !
b1000111110100101 "
b1101111100000000 $
#2560000
b100111101011011 !
b100111110001011 "
b1001111011100110 $
#2570000
b1001111010100010 !
b100111110001011 "
b1110111000101101 $
#2580000
b111111110101110 !
b100111110001011 "
b1100111100111001 $
#2590000
b10011001110110 !
b100111110001011 "
b111011000000001 $
#2600000
b10011001110110 !
b100111110001011 "
#2610000
b110101000111011 !
b110110110001100 "
b1101011111000111 $
#2620000
b110101000111011 !
b110110110001100 "
#2630000
b110101000111011 !
b110110110001100 "
#2640000
b110101000111011 !
b110110110001100 "
#2650000
b110101000111011 !
b110110110001100 "
#2660000
b1010000111101111 !
b110110110001100 "
b111101111011 $
1%
#2670000
b1010000111101111 !
b111100010101110 "
b1101010011101 $
#2680000
b111010100110110 !
b110000100001011 "
b1101011001000001 $
0%
#2690000
b111010100110110 !
b110000100001011 "
#2700000
b110110111000100 !
b111010011101000 "
b1110001010101100 $
#2710000
b110110111000100 !
b111010011101000 "
#2720000
b110110111000100 !
b1001101110100110 "
b100101101010 $
1%
#2730000
b1001001010011011 !
b101000110100110 "
b1110010001000001 $
0%
#2740000
b11110101101110 !
b101000110100110 "
b1000111100010100 $
#2750000
b11110101101110 !
b111001001000011 "
b1010111110110001 $
#2760000
b1010010110100000 !
b101101100001111 "
b10101111 $
1%
#2770000
b1001100100001101 !
b101101100001111 "
b1111010000011100 $
0%
#2780000
b1000001101111101 !
b1001011110110011 "
b1101100110000 $
1%
#2790000
b1011000011110011 !
b1001011110110011 "
b100100010100110 $
#2800000
b1011000011110011 !
b110101001111001 "
b1101101101100 $
#2810000
b1011000011110011 !
b110110110101011 "
b1111010011110 $
#2820000
b11111000000110 !
b110110110101011 "
b1010101110110001 $
0%
#2830000
b111111110011011 !
b110110110101011 "
b1110110101000110 $
#2840000
b111111110011011 !
b1000000101001011 "
b11100110 $
1%
#2850000
b111111110010101 !
b110110111011001 "
b1110110101101110 $
0%
#2860000
b1000011010111010 !
b1010001100010010 "
b10100111001100 $
1%
#2870000
b1000011010111010 !
b111100001001100 "
b1111111100000110 $
0%
#2880000
b1000111010000101 !
b111100001001100 "
b11011010001 $
1%
#2890000
b1000111010000101 !
b110000010011100 "
b1110111100100001 $
0%
#2900000
b1011100011111000 !
b110000010011100 "
b1100110010100 $
1%
#2910000
b1010001011001100 !
b110000010011100 "
b1101101000 $
#2920000
b1001011010100010 !
b110000010011100 "
b1111011100111110 $
0%
#2930000
b1010010110000000 !
b1000101000010011 "
b10111110010011 $
1%
#2940000
b1010010110000000 !
b1000101000010011 "
#2950000
b1010010110000000 !
b1000101000010011 "
#2960000
b1010010110000000 !
b1000101000010011 "
#2970000
b1010010110000000 !
b110110001010001 "
b1000111010001 $
#2980000
b111011011110111 !
b1010100010000111 "
b1111101111110 $
#2990000
b111011011110111 !
b1010100010000111 "
#3000000
b1000001111000100 !
b1010100010000111 "
b10110001001011 $
#3010000
b1000001111000100 !
b111001000101011 "
b1111010111101111 $
0%
#3020000
b1000001111000100 !
b101100111100001 "
b1101110110100101 $
#3030000
b110110110100110 !
b111001010000111 "
b1110000000101101 $
#3040000
b110110110100110 !
b111001010000111 "
#3050000
b110110110100110 !
b1010111001101010 "
b1110000010000 $
1%
#3060000
b101111001110000 !
b1010111001101010 "
b110011011010 $
#3070000
b101111001110000 !
b1000111100011101 "
b1110110110001101 $
0%
#3080000
b101111001110000 !
b1000111100011101 "
#3090000
b110111110011100 !
b1000100000001111 "
b1111011110101011 $
#3100000
b110110001001111 !
b111000111101000 "
b1101111000110111 $
#3110000
b1100101110111011 !
b111000111101000 "
b11110110100011 $
1%
#3120000
b100011100000110 !
b1000010001011111 "
b1100101101100101 $
0%
#3130000
b100011100000110 !
b1000010100011100 "
b1100110000100010 $
#3140000
b1001101000001110 !
b1000010100011100 "
b1111100101010 $
1%
#3150000
b110010000111111 !
b1000010100011100 "
b1110100101011011 $
0%
#3160000
b110010000111111 !
b111010010111000 "
b1101100011110111 $
#3170000
b110010000111111 !
b111010010111000 "
#3180000
b110010000111111 !
b1010101100101101 "
b111101101100 $
1%
#3190000
b1000101110110100 !
b1010110001110000 "
b11100000100100 $
#3200000
b1000101110110100 !
b1010110001110000 "
#3210000
b1010111000101111 !
b1010110001110000 "
b101101010011111 $
#3220000
b110000100100101 !
b1010110001110000 "
b110110010101 $
#3230000
b110000100100101 !
b1010110001110000 "
#3240000
b110000100100101 !
b111110111001101 "
b1101111011110010 $
0%
#3250000
b110000100100101 !
b111000100010110 "
b1101001000111011 $
#3260000
b1001000010000010 !
b1000110101110000 "
b1110111110010 $
1%
#3270000
b110100010100010 !
b1000011101001000 "
b1110111111101010 $
0%
#3280000
b110100010100010 !
b101011011111110 "
b1011111110100000 $
#3290000
b1000101100010001 !
b101011011111110 "
b1110001000001111 $
#3300000
b1000101100010001 !
b110111100111000 "
b1111101001001001 $
#3310000
b1001101001111100 !
b110010010111101 "
b1111111100111001 $
0%
#3320000
b1001101001111100 !
b1000111000111001 "
b10100010110101 $
1%
#3330000
b1010011110110000 !
b1000010011100101 "
b10110010010101 $
#3340000
b1001000101101011 !
b111000000111010 "
b110100101 $
#3350000
b1001000101101011 !
b1000110001100010 "
b1110111001101 $
#3360000
b1001000111010001 !
b1000110001100010 "
b1111000110011 $
#3370000
b111100100101000 !
b110011111000101 "
b1110000011101101 $
0%
#3380000
b111100100101000 !
b1101010110100100 "
b100111011001100 $
1%
#3390000
b1001100010011000 !
b1001011101001111 "
b10111111100111 $
#3400000
b1010000101111000 !
b1001011101001111 "
b11100011000111 $
#3410000
b11010101110111 !
b1001001100000011 "
b1100100001111010 $
0%
#3420000
b11010101110111 !
b1001001100000011 "
#3430000
b11010101110111 !
b111010101110110 "
b1010101011101101 $
#3440000
b110111100010111 !
b1000100010000001 "
b1111011110011000 $
#3450000
b1000011000110011 !
b1000100010000001 "
b111010110100 $
1%
#3460000
b1000011000110011 !
b1000100010000001 "
#3470000
b1000011000110011 !
b10000111111010 "
b1010100000101101 $
0%
#3480000
b1000011000110011 !
b101110101011100 "
b1110001110001111 $
#3490000
b110100010011110 !
b1001101100100000 "
b1110111110 $
1%
#3500000
b1001001001100001 !
b111100101100101 "
b101111000110 $
#3510000
b1001001001100001 !
b1001100010011010 "
b10101011111011 $
#3520000
b1001001001100001 !
b1001100010011010 "
#3530000
b1001001001100001 !
b1001100010011010 "
#3540000
b1001001001100001 !
b1001100010011010 "
#3550000
b1001001001100001 !
b110100110000001 "
b1111101111100010 $
0%
#3560000
b111101110101110 !
b1010000010110001 "
b1110001011111 $
1%
#3570000
b111101110101110 !
b1000111001110010 "
b101000100000 $
1%
#3580000
b110000101100101 !
b111111010100100 "
b1110000000001001 $
0%
#3590000
b100111111011011 !
b111010011101110 "
b1100010011001001 $
#3600000
b10110010101010 !
b111010011101110 "
b1010000110011000 $
#3610000
b1000011011100110 !
b101110001000100 "
b1110001100101010 $
0%
#3620000
b1000011110011100 !
b110001101110110 "
b1110101100010010 $
#3630000
b1000011110011100 !
b110001101110110 "
#3640000
b110011110101010 !
b110001101110110 "
b1100101100100000 $
#3650000
b110011110101010 !
b110001101110110 "
#3660000
b1001101001010101 !
b1000101101111111 "
b10010111010100 $
1%
#3670000
b1001101001010101 !
b1000101101111111 "
#3680000
b1001101001010101 !
b1000101101111111 "
#3690000
b111000000100100 !
b1000101101111111 "
b1111101110100011 $
0%
#3700000
b1000101101100111 !
b1000011100010001 "
b1001001111000 $
1%
#3710000
b1000101111100111 !
b1010001001101100 "
b10111001010011 $
#3720000
b1000101111100111 !
b1010001001101100 "
#3730000
b1000101111100111 !
b1010001001101100 "
#3740000
b110011011111000 !
b110110011000111 "
b1101001110111111 $
0%
#3750000
b1000001110101011 !
b110110111111001 "
b1111000110100100 $
#3760000
b1000001110101011 !
b110110111111001 "
#3770000
b110111011101010 !
b110011100011100 "
b1101011000000110 $
#3780000
b110111011101010 !
b111100011010111 "
b1110011111000001 $
#3790000
b110111011101010 !
b1000110111111000 "
b1111110011100010 $
#3800000
b110010010010111 !
b1011000011010100 "
b1010101101011 $
1%
#3810000
b110010010010111 !
b1001101011111010 "
b1111111110010001 $
0%
#3820000
b110010010010111 !
b111110111111101 "
b1110001010010100 $
#3830000
b111001101011001 !
b111110111111101 "
b1111000101010110 $
#3840000
b111001101011001 !
b111110111111101 "
#3850000
b1001110001011011 !
b100101110000001 "
b1110011111011100 $
#3860000
b1001110001011011 !
b110101111101101 "
b100001001000 $
1%
#3870000
b111101011110100 !
b110101111101101 "
b1110011011100001 $
0%
#3880000
b111101011110100 !
b110101111101101 "
#3890000
b110010011101100 !
b110101111101101 "
b1101000011011001 $
#3900000
b111001110111100 !
b110101111101101 "
b1101111110101001 $
#3910000
b10100101011111 !
b110101111101101 "
b1001010101001100 $
#3920000
b10100101011111 !
b110010111010010 "
b1000111100110001 $
#3930000
b10100101011111 !
b110010111010010 "
#3940000
b10100101011111 !
b110010111010010 "
#3950000
b10100101011111 !
b110010111010010 "
#3960000
b1001010010110000 !
b110010111010010 "
b1111101010000010 $
0%
#3970000
b1001010010110000 !
b111110011010011 "
b1000110000011 $
1%
#3980000
b1001010010110000 !
b111110011010011 "
#3990000
b101000001000110 !
b111110011010011 "
b1100110100011001 $
0%
#4000000
b101000001000110 !
b111110011010011 "
#4010000
b111100100110111 !
b111110011010011 "
b1111011000001010 $
#4020000
b111100100110111 !
b111110011010011 "
#4030000
b111100100110111 !
b111110011010011 "
#4040000
b111100100110111 !
b1001100010001010 "
b1000111000001 $
1%
#4050000
b1001101101010010 !
b101110010100000 "
b1111011111110010 $
0%
#4060000
b1001110011000110 !
b1010110110010010 "
b100101001011000 $
1%
#4070000
b111100100011011 !
b1010110110010010 "
b10011010101101 $
#4080000
b111100100011011 !
b1000111100001000 "
b100000100011 $
#4090000
b111100010101110 !
b1000111100001000 "
b11110110110 $
