old_src/full_adder.v
`timescale 1ns / 1ps

module full_adder(
    input a, 
    input b, 
    input cin, 
    output sum, 
    output cout
);

assign sum = a ^ b ^ cin;
assign cout = (a & b) | (b & cin) | (a & cin);

endmodule

old_src/rca_8bit.v
`timescale 1ns / 1ps

module rca_8bit(
    input [7:0] a,
    input [7:0] b,
    input cin,
    output [7:0] sum,
    output cout
);
    
    wire [6:0] c;

    full_adder fa0 (a[0], b[0], cin, sum[0], c[0]);
    full_adder fa1 (a[1], b[1], c[0], sum[1], c[1]);
    full_adder fa2 (a[2], b[2], c[1], sum[2], c[2]);
    full_adder fa3 (a[3], b[3], c[2], sum[3], c[3]);
    full_adder fa4 (a[4], b[4], c[3], sum[4], c[4]);
    full_adder fa5 (a[5], b[5], c[4], sum[5], c[5]);
    full_adder fa6 (a[6], b[6], c[5], sum[6], c[6]);
    full_adder fa7 (a[7], b[7], c[6], sum[7], cout);

endmodule

old_src/rca_16bit.v
`timescale 1ns / 1ps

module rca_16bit(
    input [15:0] a,
    input [15:0] b,
    input cin,
    output [15:0] sum,
    output cout
);
    
    wire c8;
    
    rca_8bit low (a[7:0], b[7:0], cin, sum[7:0], c8);
    rca_8bit high (a[15:8], b[15:8], c8, sum[15:8], cout);

endmodule

old_src/sim_rca_16bit_uniform.v
`timescale 1ns/1ps

module sim_rca_16bit_uniform;

    reg  [15:0] a, b;
    reg cin;
    wire [15:0] sum;
    wire cout;

    // Arquivos
    integer in_file;
    integer out_file;
    integer r;
    
    rca_16bit DUT (
        .a(a),
        .b(b),
        .cin(cin),
        .sum(sum),
        .cout(cout)
    );

        // Caminhos de arquivo de entrada e saída
    reg [1023:0] input_file  = "/home/tiago/energetic_efficiency/data/16_uniform.txt";
    reg [1023:0] output_file = "/home/tiago/energetic_efficiency/results/rca_16bit_uniform.txt";
//     
    initial begin
        // Abre arquivos
        in_file  = $fopen(input_file, "r");
        out_file = $fopen(output_file, "w");

        if(in_file == 0) begin
            $display("Erro ao abrir arquivo de entrada: %s", input_file);
            $finish;
        end
        if(out_file == 0) begin
            $display("Erro ao abrir arquivo de saída: %s", output_file);
            $finish;
        end

        $display("Simulação iniciada: %s -> %s", input_file, output_file);

        // fixa o carry-in
        cin = 0;

        // Processamento Sequencial Sem Clock Rápido
        while (!$feof(in_file)) begin
            // 1. Lê os dados do arquivo
            r = $fscanf(in_file, "%h %h\n", a, b);
            
            // 2. Aguarda um tempo para a lógica combinacional estabilizar
            // 10ns é mais que suficiente para um RCA de 16 bits na Spartan-7
            #10; 
            
            // 3. Grava a entrada E a saída resultante na mesma linha
            $fwrite(out_file, "%h %h %b %h %b\n", a, b, cin, sum, cout);
        end

        $fclose(in_file);
        $fclose(out_file);

        $display("Simulação concluída.");
        $finish;
    end

endmodule

results/sim_rca_16bit_uniform.vcd
$date
   Wed Mar 18 13:43:40 2026
$end
$version
  2022.1
$end
$timescale
  1ps
$end
$scope module sim_rca_16bit_uniform $end
$var reg 16 ! a [15:0] $end
$var reg 16 " b [15:0] $end
$var reg 1 # cin $end
$var wire 16 $ sum [15:0] $end
$var wire 1 % cout $end
$var integer 32 & in_file [31:0] $end
$var integer 32 ' out_file [31:0] $end
$var integer 32 ( r [31:0] $end
$var reg 1024 ) input_file [1023:0] $end
$var reg 1024 * output_file [1023:0] $end
$upscope $end
$enddefinitions $end
#0
$dumpvars
b1101110001100110 !
b1001110110011001 "
0#
b111100111111111 $
1%
b11111111111111111011000111100000 &
b11111111111111111011000111100001 '
b10 (
b101111011010000110111101101101011001010010111101110100011010010110000101100111011011110010111101100101011011100110010101110010011001110110010101110100011010010110001101011111011001010110011001100110011010010110001101101001011001010110111001100011011110010010111101100100011000010111010001100001001011110011000100110110010111110111010101101110011010010110011001101111011100100110110100101110011101000111100001110100 )
b10111101101000011011110110110101100101001011110111010001101001011000010110011101101111001011110110010101101110011001010111001001100111011001010111010001101001011000110101111101100101011001100110011001101001011000110110100101100101011011100110001101111001001011110111001001100101011100110111010101101100011101000111001100101111011100100110001101100001010111110011000100110110011000100110100101110100010111110111010101101110011010010110011001101111011100100110110100101110011101000111100001110100 *
$end
#10000
b1101110001100110 !
b11011000011001 "
b1001001111111 $
1%
#20000
b1101011100 !
b11011000011001 "
b11100101110101 $
0%
#30000
b1001010100001110 !
b11011000011001 "
b1100101100100111 $
#40000
b1001010100001110 !
b101001011011110 "
b1110011111101100 $
#50000
b1101010001000111 !
b1001010101010010 "
b110100110011001 $
1%
#60000
b1101010001000111 !
b110011000101011 "
b11101001110010 $
#70000
b10110000010100 !
b110011000101011 "
b1001001000111111 $
0%
#80000
b10110000010100 !
b110011000101011 "
#90000
b1100001111001 !
b110011000101011 "
b111111010100100 $
#100000
b100000111010010 !
b1101000011000 "
b101101111101010 $
#110000
b100000111010010 !
b1101000011000 "
#120000
b1001000101001010 !
b1100100100100100 "
b101101001101110 $
1%
#130000
b1001000101001010 !
b1100100100100100 "
#140000
b1001000101001010 !
b1011111101101111 "
b101000010111001 $
#150000
b1110110101110100 !
b1100011011000000 "
b1011010000110100 $
#160000
b1110110101110100 !
b1100111000000001 "
b1011101101110101 $
#170000
b1110101101100111 !
b1100111000000001 "
b1011100101101000 $
#180000
b1110101101100111 !
b1100111000000001 "
#190000
b1110101101100111 !
b101100000011111 "
b100001110000110 $
#200000
b11010010101 !
b101100000011111 "
b101111010110100 $
0%
#210000
b1111110100110100 !
b1010110011001001 "
b1010100111111101 $
1%
#220000
b1111110100110100 !
b1010110011001001 "
#230000
b1111110100110100 !
b1100011010110001 "
b1100001111100101 $
#240000
b1111110100110100 !
b1100011010110001 "
#250000
b1111110110011101 !
b1100011010110001 "
b1100010001001110 $
#260000
b1111110110011101 !
b11110100100100 "
b11101011000001 $
#270000
b100110000001 !
b1101011001011 "
b10010001001100 $
0%
#280000
b100110000001 !
b1000001011110000 "
b1000110001110001 $
#290000
b1001001110111011 !
b1000001011110000 "
b1011010101011 $
1%
#300000
b1001100100010100 !
b1100000001110010 "
b101100110000110 $
#310000
b1001100100010100 !
b1011101011010001 "
b101001111100101 $
#320000
b1101000111001011 !
b1011101011010001 "
b1000110010011100 $
#330000
b1101000111001011 !
b1011101011010001 "
#340000
b1101000111001011 !
b1011101011010001 "
#350000
b1101000111001011 !
b1011101011010001 "
#360000
b1111001011101011 !
b1011101011010001 "
b1010110110111100 $
#370000
b110101101011000 !
b110101001 "
b110110100000001 $
0%
#380000
b110101101011000 !
b1111111001101 "
b1000101100100101 $
#390000
b1010000111011010 !
b1111111001101 "
b1100000110100111 $
#400000
b110010000111010 !
b1111111001101 "
b1000010000000111 $
#410000
b110010000111010 !
b1100001101000001 "
b10011101111011 $
1%
#420000
b110010000111010 !
b111110000111011 "
b1110000001110101 $
0%
#430000
b100011111111111 !
b1011011111101100 "
b1111111111101011 $
0%
#440000
b100011111111111 !
b1011011111101100 "
#450000
b101010111011 !
b1011011111101100 "
b1100001010100111 $
#460000
b101010111011 !
b100111001110111 "
b101100100110010 $
#470000
b1110011100001110 !
b10110000000 "
b1110110010001110 $
#480000
b10111101 !
b100110110011001 "
b100111001010110 $
#490000
b10111101 !
b1101100000101001 "
b1101100011100110 $
#500000
b10111101 !
b1001011010111101 "
b1001011101111010 $
#510000
b1000101110111101 !
b1010100001111010 "
b11010000110111 $
1%
#520000
b1000101110111101 !
b1001101010111100 "
b10011001111001 $
#530000
b11101101011 !
b1001100011111011 "
b1010000001100110 $
0%
#540000
b11101101011 !
b1111001111001100 "
b1111101100110111 $
0%
#550000
b11101101011 !
b1111001111001100 "
#560000
b11101101011 !
b1111001111001100 "
#570000
b1100010111111000 !
b1111001111001100 "
b1011100111000100 $
1%
#580000
b10110010000010 !
b1111001111001100 "
b10000001001110 $
#590000
b110111100100 !
b1111001111001100 "
b110110000 $
#600000
b111100110010 !
b1101100100001011 "
b1110100000111101 $
0%
#610000
b1010001010000110 !
b1011101111101101 "
b101111001110011 $
1%
#620000
b111100000010100 !
b1011101111101101 "
b11010000000001 $
#630000
b111100000010100 !
b110101011000010 "
b1110001011010110 $
0%
#640000
b11100010100110 !
b111001000011011 "
b1010101011000001 $
#650000
b11100010100110 !
b1001001011000001 "
b1100101101100111 $
#660000
b10100110000011 !
b1001001011000001 "
b1011110001000100 $
#670000
b10100110000011 !
b1011101111110010 "
b1110010101110101 $
#680000
b10100110000011 !
b11011011110 "
b11000001100001 $
#690000
b1010100000001101 !
b11011011110 "
b1010111011101011 $
#700000
b1010100000001101 !
b11011011110 "
#710000
b1010100000001101 !
b1111010010000110 "
b1001110010010011 $
1%
#720000
b10101100001000 !
b111000111110001 "
b1001110011111001 $
0%
#730000
b10101100001000 !
b111000111110001 "
#740000
b101000110100 !
b111111001011110 "
b1000100010010010 $
#750000
b1101101110000001 !
b1010001100001101 "
b111111010001110 $
1%
#760000
b1101101110000001 !
b111111110100110 "
b101101100100111 $
#770000
b1101100001011011 !
b111111110100110 "
b101100000000001 $
#780000
b1101010101101110 !
b1011000001111101 "
b1000010111101011 $
#790000
b1101010101101110 !
b1011000001111101 "
#800000
b1101010101101110 !
b1011000001111101 "
#810000
b1101010101101110 !
b1011000001111101 "
#820000
b1101010101101110 !
b1011000001111101 "
#830000
b1101010101101110 !
b1011000001111101 "
#840000
b1010111110101110 !
b1011000001111101 "
b110000000101011 $
#850000
b1010111110101110 !
b1100010111011100 "
b111010110001010 $
#860000
b11100011001101 !
b111010100100101 "
b1010110111110010 $
0%
#870000
b11100011001101 !
b111010100100101 "
#880000
b11100011001101 !
b111010100100101 "
#890000
b11100011001101 !
b111010100100101 "
#900000
b11100011001101 !
b111010100100101 "
#910000
b11100011001101 !
b10001000000011 "
b101101011010000 $
#920000
b11100011001101 !
b1011111100101111 "
b1111011111111100 $
#930000
b11100011001101 !
b1011111100101111 "
#940000
b11100011001101 !
b1111100100111011 "
b11001000001000 $
1%
#950000
b1010101000110101 !
b1011011010100111 "
b110000011011100 $
#960000
b1010101000110101 !
b1011011010100111 "
#970000
b1100111100000011 !
b1011011010100111 "
b1000010110101010 $
#980000
b1100111100000011 !
b1011011010100111 "
#990000
b10010111011100 !
b1011011010100111 "
b1101110010000011 $
0%
#1000000
b10010111011100 !
b101100100111001 "
b111111100010101 $
#1010000
b1111100110010001 !
b100110010111000 "
b100011001001001 $
1%
#1020000
b1101011011001 !
b100110010111000 "
b110011110010001 $
0%
#1030000
b1101011011001 !
b1000111001001000 "
b1010100100100001 $
#1040000
b10100001 !
b1000111001001000 "
b1000111011101001 $
#1050000
b1001000011001001 !
b10011000001100 "
b1011011011010101 $
#1060000
b1001000011001001 !
b10011000001100 "
#1070000
b1000001111100011 !
b10011000001100 "
b1010100111101111 $
#1080000
b1000001111100011 !
b101110000010100 "
b1101111111110111 $
#1090000
b1000001111100011 !
b1101100011111100 "
b101110011011111 $
1%
#1100000
b1000001111100011 !
b1101100011111100 "
#1110000
b10110100001110 !
b1101100011111100 "
b11000001010 $
1%
#1120000
b111000111000111 !
b10100100000001 "
b1001101011001000 $
0%
#1130000
b111000111000111 !
b1010111100101011 "
b10000011110010 $
1%
#1140000
b1110111011010110 !
b100101111100111 "
b11101010111101 $
#1150000
b110010011111011 !
b100101111100111 "
b1011000011100010 $
0%
#1160000
b1111111000 !
b1100011111010110 "
b1100101111001110 $
0%
#1170000
b1111111000 !
b1100011111010110 "
#1180000
b1111111000 !
b1011100110110 "
b1101100101110 $
#1190000
b101111011010100 !
b100101000100111 "
b1010100011111011 $
#1200000
b101101011001111 !
b100101000100111 "
b1010010011110110 $
#1210000
b101101011001111 !
b1111111001100000 "
b101100100101111 $
1%
#1220000
b10000101010001 !
b1011000011011111 "
b1101001000110000 $
0%
#1230000
b10000101010001 !
b1011000011011111 "
#1240000
b10010000110100 !
b1110000100010111 "
b10101001011 $
1%
#1250000
b101001100010111 !
b1110000100010111 "
b11010000101110 $
#1260000
b10111110011001 !
b1110000100010111 "
b1000010110000 $
#1270000
b1111100011011000 !
b1110000100010111 "
b1101100111101111 $
#1280000
b1111100011011000 !
b11111111101 "
b11010101 $
1%
#1290000
b1111100011011000 !
b101111001110100 "
b101011101001100 $
#1300000
b1111100011011000 !
b101111001110100 "
#1310000
b1111100011011000 !
b101111001110100 "
#1320000
b1001110000101000 !
b101111001110100 "
b1111101010011100 $
0%
#1330000
b1001110000101000 !
b101111001110100 "
#1340000
b1001110000101000 !
b1101110110110010 "
b111100111011010 $
1%
#1350000
b1110111100101100 !
b1011110110010101 "
b1010110011000001 $
#1360000
b1100000001000000 !
b1011110110010101 "
b111110111010101 $
#1370000
b1011111101011000 !
b1011110110010101 "
b111110011101101 $
#1380000
b1001111101000110 !
b1011100111001001 "
b101100100001111 $
#1390000
b1001111101000110 !
b1011100111001001 "
#1400000
b1001111101000110 !
b1011100111001001 "
#1410000
b1001111101000110 !
b1011100111001001 "
#1420000
b11111101011 !
b1000000000101100 "
b1000100000010111 $
0%
#1430000
b101010000111 !
b1100100000100101 "
b1101001010101100 $
#1440000
b1110010111010111 !
b1100100000100101 "
b1010110111111100 $
1%
#1450000
b1110010111010111 !
b101100011110100 "
b11111011001011 $
#1460000
b1010010001010 !
b101100011110100 "
b110110101111110 $
0%
#1470000
b101010111110010 !
b101100011110100 "
b1010111011100110 $
#1480000
b101010111110010 !
b1111001011111 "
b111010001010001 $
#1490000
b1000000110000111 !
b1111001011111 "
b1001111111100110 $
#1500000
b11011010100010 !
b1101010011111011 "
b101110011101 $
1%
#1510000
b1111000110100010 !
b1101010011111011 "
b1100011010011101 $
#1520000
b1111100100100000 !
b11010000111100 "
b10110101011100 $
#1530000
b1111100100100000 !
b11010000111100 "
#1540000
b1001011100000100 !
b111010001110110 "
b101101111010 $
#1550000
b110111101001 !
b1111000001010110 "
b1111111000111111 $
0%
#1560000
b110100011100110 !
b1111000001010110 "
b101100100111100 $
1%
#1570000
b1111101111111001 !
b101100001001111 "
b101010001001000 $
#1580000
b1111101111111001 !
b101100001001111 "
#1590000
b1100110000011011 !
b101100001001111 "
b10010001101010 $
#1600000
b101100010000110 !
b101100001001111 "
b1011000011010101 $
0%
#1610000
b101100010000110 !
b101100001001111 "
#1620000
b111011101000111 !
b101100001001111 "
b1100111110010110 $
#1630000
b111011101000111 !
b101100001001111 "
#1640000
b1011101110100001 !
b111011001000110 "
b11000111100111 $
1%
#1650000
b1011101110100001 !
b1101101110110011 "
b1001011101010100 $
#1660000
b1011101110100001 !
b1101101110110011 "
#1670000
b1011101110100001 !
b1010101101000111 "
b110011011101000 $
#1680000
b1011101110100001 !
b10000000011000 "
b1101101110111001 $
0%
#1690000
b10111000111101 !
b10011100010110 "
b101010101010011 $
#1700000
b10111000111101 !
b10011100010110 "
#1710000
b1110001100100100 !
b10011100010110 "
b101000111010 $
1%
#1720000
b111100001100010 !
b1000010011100000 "
b1111110101000010 $
0%
#1730000
b100101010101011 !
b1000010011100000 "
b1100111110001011 $
#1740000
b1111011101100111 !
b1011110111111101 "
b1011010101100100 $
1%
#1750000
b1111011101100111 !
b1011110111111101 "
#1760000
b101111111011010 !
b100101100011010 "
b1010101011110100 $
0%
#1770000
b101111111011010 !
b1110111001110100 "
b100111001001110 $
1%
#1780000
b1001111000000 !
b1001011001000010 "
b1010101000000010 $
0%
#1790000
b1001111000000 !
b100011000101110 "
b101100111101110 $
#1800000
b1001111000000 !
b1001011110000 "
b10011010110000 $
#1810000
b1001111000000 !
b1001011110000 "
#1820000
b1001111000000 !
b10111000000111 "
b100000111000111 $
#1830000
b1001111000000 !
b10111000000111 "
#1840000
b1100111100000000 !
b10111000000111 "
b1111110100000111 $
0%
#1850000
b100010000000100 !
b1111000110101001 "
b11010110101101 $
1%
#1860000
b100010000000100 !
b1111000110101001 "
#1870000
b100010000000100 !
b1111000110101001 "
#1880000
b1101011111110 !
b1111000110101001 "
b110010100111 $
1%
#1890000
b1011000110001101 !
b1111000110101001 "
b1010001100110110 $
#1900000
b110001101100110 !
b1111000110101001 "
b101010100001111 $
#1910000
b1101101100011010 !
b1111000110101001 "
b1100110011000011 $
#1920000
b1101101100011010 !
b1111000110101001 "
#1930000
b11001110 !
b1111000110101001 "
b1111001001110111 $
0%
#1940000
b11001110 !
b1111000110101001 "
#1950000
b11001110 !
b1001100000110110 "
b1001100100000100 $
#1960000
b1101111000101001 !
b1111110001000 "
b1111110110110001 $
#1970000
b101101101111011 !
b1111110001000 "
b111101100000011 $
#1980000
b1100010111001100 !
b1111110001000 "
b1110010101010100 $
#1990000
b1100010111001100 !
b1010111010001111 "
b111010001011011 $
1%
#2000000
b1011111000111110 !
b1010111010001111 "
b110110011001101 $
#2010000
b1100001101011111 !
b1010111010001111 "
b111000111101110 $
#2020000
b1100101011100110 !
b1010011011000111 "
b111000110101101 $
#2030000
b1101110011110000 !
b1010011011000111 "
b1000001110110111 $
#2040000
b1010001000110011 !
b1010011011000111 "
b100100011111010 $
#2050000
b1101001111111100 !
b1010011011000111 "
b111101011000011 $
#2060000
b1011000001011111 !
b110100011011011 "
b1100100111010 $
1%
#2070000
b1011000001011111 !
b110100011011011 "
#2080000
b100011011011101 !
b1010101110010 "
b101110001001111 $
0%
#2090000
b100011011011101 !
b101010011010111 "
b1001101110110100 $
#2100000
b100011011011101 !
b1100000000110000 "
b11100001101 $
1%
#2110000
b100011011011101 !
b1001011100011100 "
b1101110111111001 $
0%
#2120000
b1101101011101100 !
b1001011100011100 "
b111001000001000 $
1%
#2130000
b11010001110 !
b111100001110101 "
b111111100000011 $
0%
#2140000
b11010001110 !
b1101100001010001 "
b1101111011011111 $
#2150000
b11010001110 !
b1010110100000110 "
b1011001110010100 $
#2160000
b1000010000100011 !
b1100111001001100 "
b101001001101111 $
1%
#2170000
b1101101000001100 !
b1100111001001100 "
b1010100001011000 $
#2180000
b1101101000001100 !
b1100111001001100 "
#2190000
b11111101000110 !
b1100111001001100 "
b110110010010 $
#2200000
b11111101000110 !
b1000001001111001 "
b1100000110111111 $
0%
#2210000
b11111101000110 !
b1101101101000100 "
b1101010001010 $
1%
#2220000
b1100110001010101 !
b1101101101000100 "
b1010011110011001 $
#2230000
b1100110001010101 !
b1101101101000100 "
#2240000
b1010101001000001 !
b100101010100000 "
b1111010011100001 $
0%
#2250000
b1010101001000001 !
b100101010100000 "
#2260000
b1111101000101100 !
b11101100100100 "
b11010101010000 $
1%
#2270000
b1010011000111101 !
b11101100100100 "
b1110000101100001 $
0%
#2280000
b1010011000111101 !
b1110001001111110 "
b1000100010111011 $
1%
#2290000
b1010101111110100 !
b1110001001111110 "
b1000111001110010 $
#2300000
b1010101111110100 !
b1011110101100110 "
b110100101011010 $
#2310000
b111001100011011 !
b1011110101100110 "
b11000010000001 $
#2320000
b111010000011011 !
b1001000100101000 "
b10101000011 $
#2330000
b1011011001101011 !
b1001010100000011 "
b100101101101110 $
#2340000
b1011011001101011 !
b101011101010010 "
b110110111101 $
#2350000
b110010101010011 !
b10000111011010 "
b1000011100101101 $
0%
#2360000
b110010101010011 !
b10000111011010 "
#2370000
b1010011110111101 !
b1010011001101110 "
b100111000101011 $
1%
#2380000
b101010101001010 !
b1010011001101110 "
b1111101110111000 $
0%
#2390000
b101010101001010 !
b1010011001101110 "
#2400000
b110010111111001 !
b1010011001101110 "
b110001100111 $
1%
#2410000
b10011111110110 !
b1010011001101110 "
b1100111001100100 $
0%
#2420000
b10011111110110 !
b1010011001101110 "
#2430000
b10011111110110 !
b1010011001101110 "
#2440000
b10011111110110 !
b1010011001101110 "
#2450000
b10011111110110 !
b1110000101011100 "
b100101010010 $
1%
#2460000
b10011111110110 !
b1110000101011100 "
#2470000
b10011111110110 !
b100111000011110 "
b111011000010100 $
0%
#2480000
b10011111110110 !
b100111000011110 "
#2490000
b10011111110110 !
b100111000011110 "
#2500000
b1110111110111101 !
b1001010101011011 "
b1000010100011000 $
1%
#2510000
b1110111110111101 !
b1001010101011011 "
#2520000
b1110111110111101 !
b1001010101011011 "
#2530000
b1111001111001100 !
b1110101000111001 "
b1101111000000101 $
#2540000
b1111001111001100 !
b1101100011101011 "
b1100110010110111 $
#2550000
b10010100000010 !
b1100010010110100 "
b1110100110110110 $
0%
#2560000
b10010100000010 !
b1100010010110100 "
#2570000
b10010100000010 !
b1100010010110100 "
#2580000
b101010111000111 !
b1110100010000011 "
b11111001001010 $
1%
#2590000
b101010111000111 !
b1110100010000011 "
#2600000
b111001010001000 !
b1110100010000011 "
b101101100001011 $
#2610000
b1101000100111101 !
b1110100010000011 "
b1011100111000000 $
#2620000
b111010100100 !
b1110100010000011 "
b1111011100100111 $
0%
#2630000
b111110011100000 !
b1110100010000011 "
b110010101100011 $
1%
#2640000
b111110011100000 !
b1110100010000011 "
#2650000
b111110011100000 !
b1011101010001101 "
b11011101101101 $
#2660000
b1111001010101011 !
b101100110000000 "
b100110000101011 $
#2670000
b1010010111 !
b1101100111111111 "
b1101110010010110 $
0%
#2680000
b1010010111 !
b1111010000101010 "
b1111011011000001 $
#2690000
b1010010111 !
b101010111011111 "
b101100001110110 $
#2700000
b1010010111 !
b101010111011111 "
#2710000
b1110111010011111 !
b101010111011111 "
b100010001111110 $
1%
#2720000
b1110111010011111 !
b1011100000111100 "
b1010011011011011 $
#2730000
b1100010111010111 !
b1010101000101000 "
b110111111111111 $
#2740000
b110011101000 !
b1011100010001 "
b10001111111001 $
0%
#2750000
b110011101000 !
b1101100010111011 "
b1110010110100011 $
#2760000
b1101010001110000 !
b110000111000100 "
b11011000110100 $
1%
#2770000
b1101010001110000 !
b111111101001 "
b1110010001011001 $
0%
#2780000
b1101010001110000 !
b1100101101001110 "
b1001111110111110 $
1%
#2790000
b1001100110111001 !
b100010111010 "
b1010001001110011 $
0%
#2800000
b1001100110111001 !
b100010111010 "
#2810000
b1001100110111001 !
b1110111001111 "
b1011011110001000 $
#2820000
b1100110111111101 !
b1110111001111 "
b1110101111001100 $
#2830000
b1100110111111101 !
b1110111001111 "
#2840000
b1100110111111101 !
b1100010110100111 "
b1001001110100100 $
1%
#2850000
b101110110000010 !
b1100010110100111 "
b10001100101001 $
#2860000
b101110110000010 !
b1100000001100101 "
b1110111100111 $
#2870000
b11001100100 !
b1110111111010110 "
b1111011000111010 $
0%
#2880000
b100111001110000 !
b1110111111010110 "
b11111001000110 $
1%
#2890000
b100111001110000 !
b1010111001111011 "
b1111110011101011 $
0%
#2900000
b110110001010000 !
b101110010011000 "
b1100100011101000 $
#2910000
b110110001010000 !
b101110010011000 "
#2920000
b110110001010000 !
b101110010011000 "
#2930000
b110110001010000 !
b101110010011000 "
#2940000
b110110001010000 !
b1111101001000001 "
b110011010010001 $
1%
#2950000
b110110001010000 !
b10101001100010 "
b1001011010110010 $
0%
#2960000
b110110001010000 !
b111011110101110 "
b1110001111111110 $
#2970000
b110110001010000 !
b100001000010111 "
b1010111001100111 $
#2980000
b110110001010000 !
b100001000010111 "
#2990000
b1001011011011111 !
b111101011111000 "
b1000111010111 $
1%
#3000000
b1001011011011111 !
b111101011111000 "
#3010000
b1101100110000000 !
b111101011111000 "
b101010001111000 $
#3020000
b1101100110000000 !
b1001101101111111 "
b111010011111111 $
#3030000
b1011011001111101 !
b1001101101111111 "
b101000111111100 $
#3040000
b1101010010000001 !
b1001101101111111 "
b111000000000000 $
#3050000
b101010000110100 !
b1101111001010 "
b110111111111110 $
0%
#3060000
b1100011010101011 !
b1101111001010 "
b1110001001110101 $
#3070000
b1110101011011001 !
b1101111001010 "
b11010100011 $
1%
#3080000
b1110101011011001 !
b1101111001010 "
#3090000
b110011011000101 !
b1101111001010 "
b1000001010001111 $
0%
#3100000
b110011011000101 !
b1101111001010 "
#3110000
b1111100011110110 !
b1101111001010 "
b1010011000000 $
1%
#3120000
b1001101000011 !
b11110110011 "
b1101011110110 $
0%
#3130000
b1001101000011 !
b11110110011 "
#3140000
b1000000011001010 !
b11110110011 "
b1000100001111101 $
#3150000
b1010110010110111 !
b11110110011 "
b1011010001101010 $
#3160000
b1010110010110111 !
b11110110011 "
#3170000
b11000110010000 !
b11110110011 "
b11100101000011 $
#3180000
b110001011111110 !
b1000111001000111 "
b1111000101000101 $
#3190000
b1001000100100101 !
b1011101111101110 "
b100110100010011 $
1%
#3200000
b100100010111 !
b1011101111101110 "
b1100010100000101 $
0%
#3210000
b1001111101000100 !
b1011101111101110 "
b101101100110010 $
1%
#3220000
b1001111101000100 !
b1011101111101110 "
#3230000
b1001111001100001 !
b1011101111101110 "
b101101001001111 $
#3240000
b11000101 !
b110111111110100 "
b111000010111001 $
0%
#3250000
b11000101 !
b110111111110100 "
#3260000
b1000011110001010 !
b110111111110100 "
b1111011101111110 $
#3270000
b1010110111111110 !
b110111111110100 "
b1110111110010 $
1%
#3280000
b1010110111111110 !
b1111110110100111 "
b1010101110100101 $
#3290000
b101100010001111 !
b1111110110100111 "
b101011000110110 $
#3300000
b110001001100000 !
b110011111011101 "
b1100101000111101 $
0%
#3310000
b110001001100000 !
b10000111001010 "
b1000010000101010 $
#3320000
b110001001100000 !
b101100011011 "
b110110101111011 $
#3330000
b101000010111010 !
b101100011011 "
b101101111010101 $
#3340000
b101000010111010 !
b100001001010000 "
b1001001100001010 $
#3350000
b1100100111001111 !
b111110001 "
b1100101111000000 $
#3360000
b11110101011100 !
b100001010110 "
b100010110110010 $
#3370000
b110011100000010 !
b100001010110 "
b110111101011000 $
#3380000
b1100001010010011 !
b1010100100100 "
b1101011110110111 $
#3390000
b101011111011 !
b111111110011010 "
b1000101010010101 $
#3400000
b101011111011 !
b1101110100011000 "
b1110100000010011 $
0%
#3410000
b101011111011 !
b1101110100011000 "
#3420000
b101011111011 !
b1101110100011000 "
#3430000
b1110010101011001 !
b1101110100011000 "
b1100001001110001 $
1%
#3440000
b1110010101011001 !
b1101110100011000 "
#3450000
b1110010101011001 !
b1101110100011000 "
#3460000
b1010000010010010 !
b1110011010110101 "
b1000011101000111 $
#3470000
b10110010010011 !
b1110011010110101 "
b1001101001000 $
#3480000
b101101011111 !
b111010001011001 "
b111111110111000 $
0%
#3490000
b11011000110 !
b111010001011001 "
b111101100011111 $
#3500000
b100011100110011 !
b111010001011001 "
b1011101110001100 $
#3510000
b100011100110011 !
b111010001011001 "
#3520000
b100101110100000 !
b111010001011001 "
b1011111111111001 $
#3530000
b100011110100111 !
b1100111001000111 "
b1010111101110 $
1%
#3540000
b100011110100111 !
b1100111001000111 "
#3550000
b100011110100111 !
b1010110011100010 "
b1111010010001001 $
0%
#3560000
b100011110100111 !
b1010110011100010 "
#3570000
b10101101100111 !
b1010110011100010 "
b1101100001001001 $
#3580000
b10101101100111 !
b1010110011100010 "
#3590000
b11100001010 !
b1010110011100010 "
b1011001111101100 $
#3600000
b1111111011011 !
b1010110011100010 "
b1100110010111101 $
#3610000
b1111111011011 !
b10000111110 "
b10010000011001 $
#3620000
b1111111011011 !
b10000111110 "
#3630000
b1011011110110001 !
b1000011111011111 "
b11111110010000 $
1%
#3640000
b1011011110110001 !
b101001111001011 "
b101101111100 $
1%
#3650000
b1011011110110001 !
b10011010110011 "
b1101111001100100 $
0%
#3660000
b1011011110110001 !
b10011010110011 "
#3670000
b1110110100101001 !
b1011011001101110 "
b1010001110010111 $
1%
#3680000
b1110110100101001 !
b1011011001101110 "
#3690000
b100000100000110 !
b1101110101100 "
b101110010110010 $
0%
#3700000
b1011011011111011 !
b1110001110001011 "
b1001101010000110 $
1%
#3710000
b1101100010001111 !
b1110001110001011 "
b1011110000011010 $
#3720000
b1101100010001111 !
b1110001110001011 "
#3730000
b1101100010001111 !
b1110001110001011 "
#3740000
b1010001111111000 !
b1110001110001011 "
b1000011110000011 $
#3750000
b1010001111111000 !
b11011110101000 "
b1101101110100000 $
0%
#3760000
b10111000111011 !
b11011110101000 "
b110010111100011 $
#3770000
b1011001101110000 !
b110001100101000 "
b1011010011000 $
1%
#3780000
b1011001101110000 !
b110001100101000 "
#3790000
b111101110000000 !
b10100001111010 "
b1010001111111010 $
0%
#3800000
b1001010100101111 !
b10100001111010 "
b1011110110101001 $
#3810000
b1001010100101111 !
b101000010011111 "
b1110010111001110 $
#3820000
b1001010100101111 !
b1010010001111110 "
b11100110101101 $
1%
#3830000
b101000111000100 !
b1010010001111110 "
b1111011001000010 $
0%
#3840000
b1100110000100100 !
b1110111001011110 "
b1011101010000010 $
1%
#3850000
b111010010011111 !
b1110111001011110 "
b110001011111101 $
#3860000
b1110111111111010 !
b110001000000101 "
b101000111111111 $
#3870000
b1101111110110 !
b110001000000101 "
b111110111111011 $
0%
#3880000
b1101111110110 !
b100010100001000 "
b110000011111110 $
#3890000
b1110011101000 !
b100010100001000 "
b110000111110000 $
#3900000
b1110011101000 !
b1011100100011111 "
b1101011000000111 $
#3910000
b1110011101000 !
b1011000110100011 "
b1100111010001011 $
#3920000
b1110011101000 !
b110111101111111 "
b1000110001100111 $
#3930000
b1100100011001111 !
b101011000001111 "
b1111011011110 $
1%
#3940000
b1100100011001111 !
b101011000001111 "
#3950000
b1100100011001111 !
b1001011100101000 "
b101111111110111 $
#3960000
b1100010010111 !
b1001011100101000 "
b1010111110111111 $
0%
#3970000
b1101100000110101 !
b1001011100101000 "
b110111101011101 $
1%
#3980000
b1110110001110111 !
b10101111011010 "
b1100001010001 $
1%
#3990000
b1110110001110111 !
b100000111011010 "
b10111001010001 $
#4000000
b10111110010111 !
b100000111011010 "
b111000101110001 $
0%
#4010000
b10111110010111 !
b111011001111100 "
b1010011000010011 $
#4020000
b10111110010111 !
b1101111000010000 "
b110110100111 $
1%
#4030000
b1100011001110000 !
b1101111000010000 "
b1010010010000000 $
#4040000
b1100011001110000 !
b1101111000010000 "
#4050000
b1010110100011 !
b1101111000010000 "
b1111001110110011 $
0%
#4060000
b1010110100011 !
b110001000011001 "
b111011110111100 $
