old_src/full_adder.v
`timescale 1ns / 1ps

module full_adder(
    input a, 
    input b, 
    input cin, 
    output sum, 
    output cout
);

assign sum = a ^ b ^ cin;
assign cout = (a & b) | (b & cin) | (a & cin);

endmodule

old_src/rca_8bit.v
`timescale 1ns / 1ps

module rca_8bit(
    input [7:0] a,
    input [7:0] b,
    input cin,
    output [7:0] sum,
    output cout
);
    
    wire [6:0] c;

    full_adder fa0 (a[0], b[0], cin, sum[0], c[0]);
    full_adder fa1 (a[1], b[1], c[0], sum[1], c[1]);
    full_adder fa2 (a[2], b[2], c[1], sum[2], c[2]);
    full_adder fa3 (a[3], b[3], c[2], sum[3], c[3]);
    full_adder fa4 (a[4], b[4], c[3], sum[4], c[4]);
    full_adder fa5 (a[5], b[5], c[4], sum[5], c[5]);
    full_adder fa6 (a[6], b[6], c[5], sum[6], c[6]);
    full_adder fa7 (a[7], b[7], c[6], sum[7], cout);

endmodule

old_src/sim_rca_8bit.v
`timescale 1ns / 1ps

module sim_rca_8bit;

    // DUT sinais
    reg  [7:0] a, b;
    reg        cin;
    wire [7:0] sum;
    wire       cout;

    // Arquivos
    integer in_file;
    integer out_file;
    integer r;

    // DUT
    rca_8bit dut (
        .a(a),
        .b(b),
        .cin(cin),
        .sum(sum),
        .cout(cout)
    );

    // Caminhos de arquivo de entrada e saída
    reg [1023:0] input_file  = "/home/tiago/energetic_efficiency/data/8bit_all.txt";
    reg [1023:0] output_file = "/home/tiago/energetic_efficiency/results/rca_8bit_results.txt";
    
    initial begin
        // Abre arquivos
        in_file  = $fopen(input_file, "r");
        out_file = $fopen(output_file, "w");

        if(in_file == 0) begin
            $display("Erro ao abrir arquivo de entrada: %s", input_file);
            $finish;
        end
        if(out_file == 0) begin
            $display("Erro ao abrir arquivo de saída: %s", output_file);
            $finish;
        end

        $display("Simulação iniciada: %s -> %s", input_file, output_file);

        // fixa o carry-in
        cin = 0;

        // Processamento Sequencial Sem Clock Rápido
        while (!$feof(in_file)) begin
            // 1. Lê os dados do arquivo
            r = $fscanf(in_file, "%h %h\n", a, b);
            
            // 2. Aguarda um tempo para a lógica combinacional estabilizar
            // 10ns é mais que suficiente para um RCA de 16 bits na Spartan-7
            #10; 
            
            // 3. Grava a entrada E a saída resultante na mesma linha
            $fwrite(out_file, "%h %h %b %h %b\n", a, b, cin, sum, cout);
        end

        $fclose(in_file);
        $fclose(out_file);

        $display("Simulação concluída.");
        $finish;
    end

endmodule

results/sim_rca_8bit.vcd
$date
   Wed Mar 18 13:36:32 2026
$end
$version
  2022.1
$end
$timescale
  1ps
$end
$scope module sim_rca_8bit $end
$var reg 8 ! a [7:0] $end
$var reg 8 " b [7:0] $end
$var reg 1 # cin $end
$var wire 8 $ sum [7:0] $end
$var wire 1 % cout $end
$var integer 32 & in_file [31:0] $end
$var integer 32 ' out_file [31:0] $end
$var integer 32 ( r [31:0] $end
$var reg 1024 ) input_file [1023:0] $end
$var reg 1024 * output_file [1023:0] $end
$upscope $end
$enddefinitions $end
#0
$dumpvars
b0 !
b0 "
0#
b0 $
0%
b11111111111111111011000111100000 &
b11111111111111111011000111100001 '
b10 (
b10111101101000011011110110110101100101001011110111010001101001011000010110011101101111001011110110010101101110011001010111001001100111011001010111010001101001011000110101111101100101011001100110011001101001011000110110100101100101011011100110001101111001001011110110010001100001011101000110000100101111001110000110001001101001011101000101111101100001011011000110110000101110011101000111100001110100 )
b101111011010000110111101101101011001010010111101110100011010010110000101100111011011110010111101100101011011100110010101110010011001110110010101110100011010010110001101011111011001010110011001100110011010010110001101101001011001010110111001100011011110010010111101110010011001010111001101110101011011000111010001110011001011110111001001100011011000010101111100111000011000100110100101110100010111110111001001100101011100110111010101101100011101000111001100101110011101000111100001110100 *
$end
#10000
b0 !
b1 "
b1 $
#20000
b0 !
b10 "
b10 $
#30000
b0 !
b11 "
b11 $
#40000
b0 !
b100 "
b100 $
#50000
b0 !
b101 "
b101 $
#60000
b0 !
b110 "
b110 $
#70000
b0 !
b111 "
b111 $
#80000
b0 !
b1000 "
b1000 $
#90000
b0 !
b1001 "
b1001 $
#100000
b0 !
b1010 "
b1010 $
#110000
b0 !
b1011 "
b1011 $
#120000
b0 !
b1100 "
b1100 $
#130000
b0 !
b1101 "
b1101 $
#140000
b0 !
b1110 "
b1110 $
#150000
b0 !
b1111 "
b1111 $
#160000
b0 !
b10000 "
b10000 $
#170000
b0 !
b10001 "
b10001 $
#180000
b0 !
b10010 "
b10010 $
#190000
b0 !
b10011 "
b10011 $
#200000
b0 !
b10100 "
b10100 $
#210000
b0 !
b10101 "
b10101 $
#220000
b0 !
b10110 "
b10110 $
#230000
b0 !
b10111 "
b10111 $
#240000
b0 !
b11000 "
b11000 $
#250000
b0 !
b11001 "
b11001 $
#260000
b0 !
b11010 "
b11010 $
#270000
b0 !
b11011 "
b11011 $
#280000
b0 !
b11100 "
b11100 $
#290000
b0 !
b11101 "
b11101 $
#300000
b0 !
b11110 "
b11110 $
#310000
b0 !
b11111 "
b11111 $
#320000
b0 !
b100000 "
b100000 $
#330000
b0 !
b100001 "
b100001 $
#340000
b0 !
b100010 "
b100010 $
#350000
b0 !
b100011 "
b100011 $
#360000
b0 !
b100100 "
b100100 $
#370000
b0 !
b100101 "
b100101 $
#380000
b0 !
b100110 "
b100110 $
#390000
b0 !
b100111 "
b100111 $
#400000
b0 !
b101000 "
b101000 $
#410000
b0 !
b101001 "
b101001 $
#420000
b0 !
b101010 "
b101010 $
#430000
b0 !
b101011 "
b101011 $
#440000
b0 !
b101100 "
b101100 $
#450000
b0 !
b101101 "
b101101 $
#460000
b0 !
b101110 "
b101110 $
#470000
b0 !
b101111 "
b101111 $
#480000
b0 !
b110000 "
b110000 $
#490000
b0 !
b110001 "
b110001 $
#500000
b0 !
b110010 "
b110010 $
#510000
b0 !
b110011 "
b110011 $
#520000
b0 !
b110100 "
b110100 $
#530000
b0 !
b110101 "
b110101 $
#540000
b0 !
b110110 "
b110110 $
#550000
b0 !
b110111 "
b110111 $
#560000
b0 !
b111000 "
b111000 $
#570000
b0 !
b111001 "
b111001 $
#580000
b0 !
b111010 "
b111010 $
#590000
b0 !
b111011 "
b111011 $
#600000
b0 !
b111100 "
b111100 $
#610000
b0 !
b111101 "
b111101 $
#620000
b0 !
b111110 "
b111110 $
#630000
b0 !
b111111 "
b111111 $
#640000
b0 !
b1000000 "
b1000000 $
#650000
b0 !
b1000001 "
b1000001 $
#660000
b0 !
b1000010 "
b1000010 $
#670000
b0 !
b1000011 "
b1000011 $
#680000
b0 !
b1000100 "
b1000100 $
#690000
b0 !
b1000101 "
b1000101 $
#700000
b0 !
b1000110 "
b1000110 $
#710000
b0 !
b1000111 "
b1000111 $
#720000
b0 !
b1001000 "
b1001000 $
#730000
b0 !
b1001001 "
b1001001 $
#740000
b0 !
b1001010 "
b1001010 $
#750000
b0 !
b1001011 "
b1001011 $
#760000
b0 !
b1001100 "
b1001100 $
#770000
b0 !
b1001101 "
b1001101 $
#780000
b0 !
b1001110 "
b1001110 $
#790000
b0 !
b1001111 "
b1001111 $
#800000
b0 !
b1010000 "
b1010000 $
#810000
b0 !
b1010001 "
b1010001 $
#820000
b0 !
b1010010 "
b1010010 $
#830000
b0 !
b1010011 "
b1010011 $
#840000
b0 !
b1010100 "
b1010100 $
#850000
b0 !
b1010101 "
b1010101 $
#860000
b0 !
b1010110 "
b1010110 $
#870000
b0 !
b1010111 "
b1010111 $
#880000
b0 !
b1011000 "
b1011000 $
#890000
b0 !
b1011001 "
b1011001 $
#900000
b0 !
b1011010 "
b1011010 $
#910000
b0 !
b1011011 "
b1011011 $
#920000
b0 !
b1011100 "
b1011100 $
#930000
b0 !
b1011101 "
b1011101 $
#940000
b0 !
b1011110 "
b1011110 $
#950000
b0 !
b1011111 "
b1011111 $
#960000
b0 !
b1100000 "
b1100000 $
#970000
b0 !
b1100001 "
b1100001 $
#980000
b0 !
b1100010 "
b1100010 $
#990000
b0 !
b1100011 "
b1100011 $
#1000000
b0 !
b1100100 "
b1100100 $
#1010000
b0 !
b1100101 "
b1100101 $
#1020000
b0 !
b1100110 "
b1100110 $
#1030000
b0 !
b1100111 "
b1100111 $
#1040000
b0 !
b1101000 "
b1101000 $
#1050000
b0 !
b1101001 "
b1101001 $
#1060000
b0 !
b1101010 "
b1101010 $
#1070000
b0 !
b1101011 "
b1101011 $
#1080000
b0 !
b1101100 "
b1101100 $
#1090000
b0 !
b1101101 "
b1101101 $
#1100000
b0 !
b1101110 "
b1101110 $
#1110000
b0 !
b1101111 "
b1101111 $
#1120000
b0 !
b1110000 "
b1110000 $
#1130000
b0 !
b1110001 "
b1110001 $
#1140000
b0 !
b1110010 "
b1110010 $
#1150000
b0 !
b1110011 "
b1110011 $
#1160000
b0 !
b1110100 "
b1110100 $
#1170000
b0 !
b1110101 "
b1110101 $
#1180000
b0 !
b1110110 "
b1110110 $
#1190000
b0 !
b1110111 "
b1110111 $
#1200000
b0 !
b1111000 "
b1111000 $
#1210000
b0 !
b1111001 "
b1111001 $
#1220000
b0 !
b1111010 "
b1111010 $
#1230000
b0 !
b1111011 "
b1111011 $
#1240000
b0 !
b1111100 "
b1111100 $
#1250000
b0 !
b1111101 "
b1111101 $
#1260000
b0 !
b1111110 "
b1111110 $
#1270000
b0 !
b1111111 "
b1111111 $
#1280000
b0 !
b10000000 "
b10000000 $
#1290000
b0 !
b10000001 "
b10000001 $
#1300000
b0 !
b10000010 "
b10000010 $
#1310000
b0 !
b10000011 "
b10000011 $
#1320000
b0 !
b10000100 "
b10000100 $
#1330000
b0 !
b10000101 "
b10000101 $
#1340000
b0 !
b10000110 "
b10000110 $
#1350000
b0 !
b10000111 "
b10000111 $
#1360000
b0 !
b10001000 "
b10001000 $
#1370000
b0 !
b10001001 "
b10001001 $
#1380000
b0 !
b10001010 "
b10001010 $
#1390000
b0 !
b10001011 "
b10001011 $
#1400000
b0 !
b10001100 "
b10001100 $
#1410000
b0 !
b10001101 "
b10001101 $
#1420000
b0 !
b10001110 "
b10001110 $
#1430000
b0 !
b10001111 "
b10001111 $
#1440000
b0 !
b10010000 "
b10010000 $
#1450000
b0 !
b10010001 "
b10010001 $
#1460000
b0 !
b10010010 "
b10010010 $
#1470000
b0 !
b10010011 "
b10010011 $
#1480000
b0 !
b10010100 "
b10010100 $
#1490000
b0 !
b10010101 "
b10010101 $
#1500000
b0 !
b10010110 "
b10010110 $
#1510000
b0 !
b10010111 "
b10010111 $
#1520000
b0 !
b10011000 "
b10011000 $
#1530000
b0 !
b10011001 "
b10011001 $
#1540000
b0 !
b10011010 "
b10011010 $
#1550000
b0 !
b10011011 "
b10011011 $
#1560000
b0 !
b10011100 "
b10011100 $
#1570000
b0 !
b10011101 "
b10011101 $
#1580000
b0 !
b10011110 "
b10011110 $
#1590000
b0 !
b10011111 "
b10011111 $
#1600000
b0 !
b10100000 "
b10100000 $
#1610000
b0 !
b10100001 "
b10100001 $
#1620000
b0 !
b10100010 "
b10100010 $
#1630000
b0 !
b10100011 "
b10100011 $
#1640000
b0 !
b10100100 "
b10100100 $
#1650000
b0 !
b10100101 "
b10100101 $
#1660000
b0 !
b10100110 "
b10100110 $
#1670000
b0 !
b10100111 "
b10100111 $
#1680000
b0 !
b10101000 "
b10101000 $
#1690000
b0 !
b10101001 "
b10101001 $
#1700000
b0 !
b10101010 "
b10101010 $
#1710000
b0 !
b10101011 "
b10101011 $
#1720000
b0 !
b10101100 "
b10101100 $
#1730000
b0 !
b10101101 "
b10101101 $
#1740000
b0 !
b10101110 "
b10101110 $
#1750000
b0 !
b10101111 "
b10101111 $
#1760000
b0 !
b10110000 "
b10110000 $
#1770000
b0 !
b10110001 "
b10110001 $
#1780000
b0 !
b10110010 "
b10110010 $
#1790000
b0 !
b10110011 "
b10110011 $
#1800000
b0 !
b10110100 "
b10110100 $
#1810000
b0 !
b10110101 "
b10110101 $
#1820000
b0 !
b10110110 "
b10110110 $
#1830000
b0 !
b10110111 "
b10110111 $
#1840000
b0 !
b10111000 "
b10111000 $
#1850000
b0 !
b10111001 "
b10111001 $
#1860000
b0 !
b10111010 "
b10111010 $
#1870000
b0 !
b10111011 "
b10111011 $
#1880000
b0 !
b10111100 "
b10111100 $
#1890000
b0 !
b10111101 "
b10111101 $
#1900000
b0 !
b10111110 "
b10111110 $
#1910000
b0 !
b10111111 "
b10111111 $
#1920000
b0 !
b11000000 "
b11000000 $
#1930000
b0 !
b11000001 "
b11000001 $
#1940000
b0 !
b11000010 "
b11000010 $
#1950000
b0 !
b11000011 "
b11000011 $
#1960000
b0 !
b11000100 "
b11000100 $
#1970000
b0 !
b11000101 "
b11000101 $
#1980000
b0 !
b11000110 "
b11000110 $
#1990000
b0 !
b11000111 "
b11000111 $
#2000000
b0 !
b11001000 "
b11001000 $
#2010000
b0 !
b11001001 "
b11001001 $
#2020000
b0 !
b11001010 "
b11001010 $
#2030000
b0 !
b11001011 "
b11001011 $
#2040000
b0 !
b11001100 "
b11001100 $
#2050000
b0 !
b11001101 "
b11001101 $
#2060000
b0 !
b11001110 "
b11001110 $
#2070000
b0 !
b11001111 "
b11001111 $
#2080000
b0 !
b11010000 "
b11010000 $
#2090000
b0 !
b11010001 "
b11010001 $
#2100000
b0 !
b11010010 "
b11010010 $
#2110000
b0 !
b11010011 "
b11010011 $
#2120000
b0 !
b11010100 "
b11010100 $
#2130000
b0 !
b11010101 "
b11010101 $
#2140000
b0 !
b11010110 "
b11010110 $
#2150000
b0 !
b11010111 "
b11010111 $
#2160000
b0 !
b11011000 "
b11011000 $
#2170000
b0 !
b11011001 "
b11011001 $
#2180000
b0 !
b11011010 "
b11011010 $
#2190000
b0 !
b11011011 "
b11011011 $
#2200000
b0 !
b11011100 "
b11011100 $
#2210000
b0 !
b11011101 "
b11011101 $
#2220000
b0 !
b11011110 "
b11011110 $
#2230000
b0 !
b11011111 "
b11011111 $
#2240000
b0 !
b11100000 "
b11100000 $
#2250000
b0 !
b11100001 "
b11100001 $
#2260000
b0 !
b11100010 "
b11100010 $
#2270000
b0 !
b11100011 "
b11100011 $
#2280000
b0 !
b11100100 "
b11100100 $
#2290000
b0 !
b11100101 "
b11100101 $
#2300000
b0 !
b11100110 "
b11100110 $
#2310000
b0 !
b11100111 "
b11100111 $
#2320000
b0 !
b11101000 "
b11101000 $
#2330000
b0 !
b11101001 "
b11101001 $
#2340000
b0 !
b11101010 "
b11101010 $
#2350000
b0 !
b11101011 "
b11101011 $
#2360000
b0 !
b11101100 "
b11101100 $
#2370000
b0 !
b11101101 "
b11101101 $
#2380000
b0 !
b11101110 "
b11101110 $
#2390000
b0 !
b11101111 "
b11101111 $
#2400000
b0 !
b11110000 "
b11110000 $
#2410000
b0 !
b11110001 "
b11110001 $
#2420000
b0 !
b11110010 "
b11110010 $
#2430000
b0 !
b11110011 "
b11110011 $
#2440000
b0 !
b11110100 "
b11110100 $
#2450000
b0 !
b11110101 "
b11110101 $
#2460000
b0 !
b11110110 "
b11110110 $
#2470000
b0 !
b11110111 "
b11110111 $
#2480000
b0 !
b11111000 "
b11111000 $
#2490000
b0 !
b11111001 "
b11111001 $
#2500000
b0 !
b11111010 "
b11111010 $
#2510000
b0 !
b11111011 "
b11111011 $
#2520000
b0 !
b11111100 "
b11111100 $
#2530000
b0 !
b11111101 "
b11111101 $
#2540000
b0 !
b11111110 "
b11111110 $
#2550000
b0 !
b11111111 "
b11111111 $
#2560000
b1 !
b0 "
b1 $
#2570000
b1 !
b1 "
b10 $
#2580000
b1 !
b10 "
b11 $
#2590000
b1 !
b11 "
b100 $
#2600000
b1 !
b100 "
b101 $
#2610000
b1 !
b101 "
b110 $
#2620000
b1 !
b110 "
b111 $
#2630000
b1 !
b111 "
b1000 $
#2640000
b1 !
b1000 "
b1001 $
#2650000
b1 !
b1001 "
b1010 $
#2660000
b1 !
b1010 "
b1011 $
#2670000
b1 !
b1011 "
b1100 $
#2680000
b1 !
b1100 "
b1101 $
#2690000
b1 !
b1101 "
b1110 $
#2700000
b1 !
b1110 "
b1111 $
#2710000
b1 !
b1111 "
b10000 $
#2720000
b1 !
b10000 "
b10001 $
#2730000
b1 !
b10001 "
b10010 $
#2740000
b1 !
b10010 "
b10011 $
#2750000
b1 !
b10011 "
b10100 $
#2760000
b1 !
b10100 "
b10101 $
#2770000
b1 !
b10101 "
b10110 $
#2780000
b1 !
b10110 "
b10111 $
#2790000
b1 !
b10111 "
b11000 $
#2800000
b1 !
b11000 "
b11001 $
#2810000
b1 !
b11001 "
b11010 $
#2820000
b1 !
b11010 "
b11011 $
#2830000
b1 !
b11011 "
b11100 $
#2840000
b1 !
b11100 "
b11101 $
#2850000
b1 !
b11101 "
b11110 $
#2860000
b1 !
b11110 "
b11111 $
#2870000
b1 !
b11111 "
b100000 $
#2880000
b1 !
b100000 "
b100001 $
#2890000
b1 !
b100001 "
b100010 $
#2900000
b1 !
b100010 "
b100011 $
#2910000
b1 !
b100011 "
b100100 $
#2920000
b1 !
b100100 "
b100101 $
#2930000
b1 !
b100101 "
b100110 $
#2940000
b1 !
b100110 "
b100111 $
#2950000
b1 !
b100111 "
b101000 $
#2960000
b1 !
b101000 "
b101001 $
#2970000
b1 !
b101001 "
b101010 $
#2980000
b1 !
b101010 "
b101011 $
#2990000
b1 !
b101011 "
b101100 $
#3000000
b1 !
b101100 "
b101101 $
#3010000
b1 !
b101101 "
b101110 $
#3020000
b1 !
b101110 "
b101111 $
#3030000
b1 !
b101111 "
b110000 $
#3040000
b1 !
b110000 "
b110001 $
#3050000
b1 !
b110001 "
b110010 $
#3060000
b1 !
b110010 "
b110011 $
#3070000
b1 !
b110011 "
b110100 $
#3080000
b1 !
b110100 "
b110101 $
#3090000
b1 !
b110101 "
b110110 $
#3100000
b1 !
b110110 "
b110111 $
#3110000
b1 !
b110111 "
b111000 $
#3120000
b1 !
b111000 "
b111001 $
#3130000
b1 !
b111001 "
b111010 $
#3140000
b1 !
b111010 "
b111011 $
#3150000
b1 !
b111011 "
b111100 $
#3160000
b1 !
b111100 "
b111101 $
#3170000
b1 !
b111101 "
b111110 $
#3180000
b1 !
b111110 "
b111111 $
#3190000
b1 !
b111111 "
b1000000 $
#3200000
b1 !
b1000000 "
b1000001 $
#3210000
b1 !
b1000001 "
b1000010 $
#3220000
b1 !
b1000010 "
b1000011 $
#3230000
b1 !
b1000011 "
b1000100 $
#3240000
b1 !
b1000100 "
b1000101 $
#3250000
b1 !
b1000101 "
b1000110 $
#3260000
b1 !
b1000110 "
b1000111 $
#3270000
b1 !
b1000111 "
b1001000 $
#3280000
b1 !
b1001000 "
b1001001 $
#3290000
b1 !
b1001001 "
b1001010 $
#3300000
b1 !
b1001010 "
b1001011 $
#3310000
b1 !
b1001011 "
b1001100 $
#3320000
b1 !
b1001100 "
b1001101 $
#3330000
b1 !
b1001101 "
b1001110 $
#3340000
b1 !
b1001110 "
b1001111 $
#3350000
b1 !
b1001111 "
b1010000 $
#3360000
b1 !
b1010000 "
b1010001 $
#3370000
b1 !
b1010001 "
b1010010 $
#3380000
b1 !
b1010010 "
b1010011 $
#3390000
b1 !
b1010011 "
b1010100 $
#3400000
b1 !
b1010100 "
b1010101 $
#3410000
b1 !
b1010101 "
b1010110 $
#3420000
b1 !
b1010110 "
b1010111 $
#3430000
b1 !
b1010111 "
b1011000 $
#3440000
b1 !
b1011000 "
b1011001 $
#3450000
b1 !
b1011001 "
b1011010 $
#3460000
b1 !
b1011010 "
b1011011 $
#3470000
b1 !
b1011011 "
b1011100 $
#3480000
b1 !
b1011100 "
b1011101 $
#3490000
b1 !
b1011101 "
b1011110 $
#3500000
b1 !
b1011110 "
b1011111 $
#3510000
b1 !
b1011111 "
b1100000 $
#3520000
b1 !
b1100000 "
b1100001 $
#3530000
b1 !
b1100001 "
b1100010 $
#3540000
b1 !
b1100010 "
b1100011 $
#3550000
b1 !
b1100011 "
b1100100 $
#3560000
b1 !
b1100100 "
b1100101 $
#3570000
b1 !
b1100101 "
b1100110 $
#3580000
b1 !
b1100110 "
b1100111 $
#3590000
b1 !
b1100111 "
b1101000 $
#3600000
b1 !
b1101000 "
b1101001 $
#3610000
b1 !
b1101001 "
b1101010 $
#3620000
b1 !
b1101010 "
b1101011 $
#3630000
b1 !
b1101011 "
b1101100 $
#3640000
b1 !
b1101100 "
b1101101 $
#3650000
b1 !
b1101101 "
b1101110 $
#3660000
b1 !
b1101110 "
b1101111 $
#3670000
b1 !
b1101111 "
b1110000 $
#3680000
b1 !
b1110000 "
b1110001 $
#3690000
b1 !
b1110001 "
b1110010 $
#3700000
b1 !
b1110010 "
b1110011 $
#3710000
b1 !
b1110011 "
b1110100 $
#3720000
b1 !
b1110100 "
b1110101 $
#3730000
b1 !
b1110101 "
b1110110 $
#3740000
b1 !
b1110110 "
b1110111 $
#3750000
b1 !
b1110111 "
b1111000 $
#3760000
b1 !
b1111000 "
b1111001 $
#3770000
b1 !
b1111001 "
b1111010 $
#3780000
b1 !
b1111010 "
b1111011 $
#3790000
b1 !
b1111011 "
b1111100 $
#3800000
b1 !
b1111100 "
b1111101 $
#3810000
b1 !
b1111101 "
b1111110 $
#3820000
b1 !
b1111110 "
b1111111 $
#3830000
b1 !
b1111111 "
b10000000 $
#3840000
b1 !
b10000000 "
b10000001 $
#3850000
b1 !
b10000001 "
b10000010 $
#3860000
b1 !
b10000010 "
b10000011 $
#3870000
b1 !
b10000011 "
b10000100 $
#3880000
b1 !
b10000100 "
b10000101 $
#3890000
b1 !
b10000101 "
b10000110 $
#3900000
b1 !
b10000110 "
b10000111 $
#3910000
b1 !
b10000111 "
b10001000 $
#3920000
b1 !
b10001000 "
b10001001 $
#3930000
b1 !
b10001001 "
b10001010 $
#3940000
b1 !
b10001010 "
b10001011 $
#3950000
b1 !
b10001011 "
b10001100 $
#3960000
b1 !
b10001100 "
b10001101 $
#3970000
b1 !
b10001101 "
b10001110 $
#3980000
b1 !
b10001110 "
b10001111 $
#3990000
b1 !
b10001111 "
b10010000 $
#4000000
b1 !
b10010000 "
b10010001 $
#4010000
b1 !
b10010001 "
b10010010 $
#4020000
b1 !
b10010010 "
b10010011 $
#4030000
b1 !
b10010011 "
b10010100 $
#4040000
b1 !
b10010100 "
b10010101 $
#4050000
b1 !
b10010101 "
b10010110 $
#4060000
b1 !
b10010110 "
b10010111 $
#4070000
b1 !
b10010111 "
b10011000 $
#4080000
b1 !
b10011000 "
b10011001 $
#4090000
b1 !
b10011001 "
b10011010 $
#4100000
b1 !
b10011010 "
b10011011 $
#4110000
b1 !
b10011011 "
b10011100 $
#4120000
b1 !
b10011100 "
b10011101 $
#4130000
b1 !
b10011101 "
b10011110 $
#4140000
b1 !
b10011110 "
b10011111 $
#4150000
b1 !
b10011111 "
b10100000 $
#4160000
b1 !
b10100000 "
b10100001 $
#4170000
b1 !
b10100001 "
b10100010 $
#4180000
b1 !
b10100010 "
b10100011 $
#4190000
b1 !
b10100011 "
b10100100 $
#4200000
b1 !
b10100100 "
b10100101 $
#4210000
b1 !
b10100101 "
b10100110 $
#4220000
b1 !
b10100110 "
b10100111 $
#4230000
b1 !
b10100111 "
b10101000 $
#4240000
b1 !
b10101000 "
b10101001 $
#4250000
b1 !
b10101001 "
b10101010 $
#4260000
b1 !
b10101010 "
b10101011 $
#4270000
b1 !
b10101011 "
b10101100 $
#4280000
b1 !
b10101100 "
b10101101 $
#4290000
b1 !
b10101101 "
b10101110 $
#4300000
b1 !
b10101110 "
b10101111 $
#4310000
b1 !
b10101111 "
b10110000 $
#4320000
b1 !
b10110000 "
b10110001 $
#4330000
b1 !
b10110001 "
b10110010 $
#4340000
b1 !
b10110010 "
b10110011 $
#4350000
b1 !
b10110011 "
b10110100 $
#4360000
b1 !
b10110100 "
b10110101 $
#4370000
b1 !
b10110101 "
b10110110 $
#4380000
b1 !
b10110110 "
b10110111 $
#4390000
b1 !
b10110111 "
b10111000 $
#4400000
b1 !
b10111000 "
b10111001 $
#4410000
b1 !
b10111001 "
b10111010 $
#4420000
b1 !
b10111010 "
b10111011 $
#4430000
b1 !
b10111011 "
b10111100 $
#4440000
b1 !
b10111100 "
b10111101 $
#4450000
b1 !
b10111101 "
b10111110 $
#4460000
b1 !
b10111110 "
b10111111 $
#4470000
b1 !
b10111111 "
b11000000 $
#4480000
b1 !
b11000000 "
b11000001 $
#4490000
b1 !
b11000001 "
b11000010 $
#4500000
b1 !
b11000010 "
b11000011 $
#4510000
b1 !
b11000011 "
b11000100 $
#4520000
b1 !
b11000100 "
b11000101 $
#4530000
b1 !
b11000101 "
b11000110 $
#4540000
b1 !
b11000110 "
b11000111 $
#4550000
b1 !
b11000111 "
b11001000 $
#4560000
b1 !
b11001000 "
b11001001 $
#4570000
b1 !
b11001001 "
b11001010 $
#4580000
b1 !
b11001010 "
b11001011 $
#4590000
b1 !
b11001011 "
b11001100 $
#4600000
b1 !
b11001100 "
b11001101 $
#4610000
b1 !
b11001101 "
b11001110 $
#4620000
b1 !
b11001110 "
b11001111 $
#4630000
b1 !
b11001111 "
b11010000 $
#4640000
b1 !
b11010000 "
b11010001 $
#4650000
b1 !
b11010001 "
b11010010 $
#4660000
b1 !
b11010010 "
b11010011 $
#4670000
b1 !
b11010011 "
b11010100 $
#4680000
b1 !
b11010100 "
b11010101 $
#4690000
b1 !
b11010101 "
b11010110 $
#4700000
b1 !
b11010110 "
b11010111 $
#4710000
b1 !
b11010111 "
b11011000 $
#4720000
b1 !
b11011000 "
b11011001 $
#4730000
b1 !
b11011001 "
b11011010 $
#4740000
b1 !
b11011010 "
b11011011 $
#4750000
b1 !
b11011011 "
b11011100 $
#4760000
b1 !
b11011100 "
b11011101 $
#4770000
b1 !
b11011101 "
b11011110 $
#4780000
b1 !
b11011110 "
b11011111 $
#4790000
b1 !
b11011111 "
b11100000 $
#4800000
b1 !
b11100000 "
b11100001 $
#4810000
b1 !
b11100001 "
b11100010 $
#4820000
b1 !
b11100010 "
b11100011 $
#4830000
b1 !
b11100011 "
b11100100 $
#4840000
b1 !
b11100100 "
b11100101 $
#4850000
b1 !
b11100101 "
b11100110 $
#4860000
b1 !
b11100110 "
b11100111 $
#4870000
b1 !
b11100111 "
b11101000 $
#4880000
b1 !
b11101000 "
b11101001 $
#4890000
b1 !
b11101001 "
b11101010 $
#4900000
b1 !
b11101010 "
b11101011 $
#4910000
b1 !
b11101011 "
b11101100 $
#4920000
b1 !
b11101100 "
b11101101 $
#4930000
b1 !
b11101101 "
b11101110 $
#4940000
b1 !
b11101110 "
b11101111 $
#4950000
b1 !
b11101111 "
b11110000 $
#4960000
b1 !
b11110000 "
b11110001 $
#4970000
b1 !
b11110001 "
b11110010 $
#4980000
b1 !
b11110010 "
b11110011 $
#4990000
b1 !
b11110011 "
b11110100 $
#5000000
b1 !
b11110100 "
b11110101 $
#5010000
b1 !
b11110101 "
b11110110 $
#5020000
b1 !
b11110110 "
b11110111 $
#5030000
b1 !
b11110111 "
b11111000 $
#5040000
b1 !
b11111000 "
b11111001 $
#5050000
b1 !
b11111001 "
b11111010 $
#5060000
b1 !
b11111010 "
b11111011 $
#5070000
b1 !
b11111011 "
b11111100 $
#5080000
b1 !
b11111100 "
b11111101 $
#5090000
b1 !
b11111101 "
b11111110 $
#5100000
b1 !
b11111110 "
b11111111 $
#5110000
b1 !
b11111111 "
b0 $
1%
#5120000
b10 !
b0 "
b10 $
0%
#5130000
b10 !
b1 "
b11 $
#5140000
b10 !
b10 "
b100 $
#5150000
b10 !
b11 "
b101 $
#5160000
b10 !
b100 "
b110 $
#5170000
b10 !
b101 "
b111 $
#5180000
b10 !
b110 "
b1000 $
#5190000
b10 !
b111 "
b1001 $
#5200000
b10 !
b1000 "
b1010 $
#5210000
b10 !
b1001 "
b1011 $
#5220000
b10 !
b1010 "
b1100 $
#5230000
b10 !
b1011 "
b1101 $
#5240000
b10 !
b1100 "
b1110 $
#5250000
b10 !
b1101 "
b1111 $
#5260000
b10 !
b1110 "
b10000 $
#5270000
b10 !
b1111 "
b10001 $
#5280000
b10 !
b10000 "
b10010 $
#5290000
b10 !
b10001 "
b10011 $
#5300000
b10 !
b10010 "
b10100 $
#5310000
b10 !
b10011 "
b10101 $
#5320000
b10 !
b10100 "
b10110 $
#5330000
b10 !
b10101 "
b10111 $
#5340000
b10 !
b10110 "
b11000 $
#5350000
b10 !
b10111 "
b11001 $
#5360000
b10 !
b11000 "
b11010 $
#5370000
b10 !
b11001 "
b11011 $
#5380000
b10 !
b11010 "
b11100 $
#5390000
b10 !
b11011 "
b11101 $
#5400000
b10 !
b11100 "
b11110 $
#5410000
b10 !
b11101 "
b11111 $
#5420000
b10 !
b11110 "
b100000 $
#5430000
b10 !
b11111 "
b100001 $
#5440000
b10 !
b100000 "
b100010 $
#5450000
b10 !
b100001 "
b100011 $
#5460000
b10 !
b100010 "
b100100 $
#5470000
b10 !
b100011 "
b100101 $
#5480000
b10 !
b100100 "
b100110 $
#5490000
b10 !
b100101 "
b100111 $
#5500000
b10 !
b100110 "
b101000 $
#5510000
b10 !
b100111 "
b101001 $
#5520000
b10 !
b101000 "
b101010 $
#5530000
b10 !
b101001 "
b101011 $
#5540000
b10 !
b101010 "
b101100 $
#5550000
b10 !
b101011 "
b101101 $
#5560000
b10 !
b101100 "
b101110 $
#5570000
b10 !
b101101 "
b101111 $
#5580000
b10 !
b101110 "
b110000 $
#5590000
b10 !
b101111 "
b110001 $
#5600000
b10 !
b110000 "
b110010 $
#5610000
b10 !
b110001 "
b110011 $
#5620000
b10 !
b110010 "
b110100 $
#5630000
b10 !
b110011 "
b110101 $
#5640000
b10 !
b110100 "
b110110 $
#5650000
b10 !
b110101 "
b110111 $
#5660000
b10 !
b110110 "
b111000 $
#5670000
b10 !
b110111 "
b111001 $
